src/pcIrMux.vhd
library IEEE;
use IEEE.std_logic_1164.all;

entity pcIrMux is
    Port (
        A : in STD_LOGIC_VECTOR(11 downto 0); -- pc
        B : in STD_LOGIC_VECTOR(11 downto 0); -- ir
        sel : in STD_LOGIC;
        s : out STD_LOGIC_VECTOR(11 downto 0)
    );
end pcIrMux;

architecture behavioralMux of pcIrMux is

begin
    process(A, B, sel)
    begin
        if sel = '0' then
            s <= A;
        else
            s <= B;
        end if;
    end process;

end architecture behavioralMux;

src/pc.vhd
library IEEE;

use IEEE.STD_LOGIC_1164.ALL;

use IEEE.NUMERIC_STD.ALL;



entity pc is
    Port (
        data_in   : in  STD_LOGIC_VECTOR(15 downto 0);
        clk : in std_logic;
        pc_ld        : in  STD_LOGIC;
        pc_inc : in std_logic;
        reset : in std_logic;
        data_out  : out STD_LOGIC_VECTOR(11 downto 0)
    );
end pc;



architecture Behavioral_PC of pc is
    signal counter : unsigned(11 downto 0) := (others => '0');

begin

process(reset, clk)
begin
    if rising_edge(clk) then
        if reset = '1' then
            counter <= (others => '0');
        elsif pc_ld = '1' then
                counter <= unsigned(data_in(11 downto 0));
        elsif pc_inc = '1' then
                counter <= counter + 1;
        end if;
    end if;
end process;

       data_out <= std_logic_vector(counter);

end Behavioral_PC;

src/ir.vhd
library IEEE;

use IEEE.STD_LOGIC_1164.ALL;

use IEEE.NUMERIC_STD.ALL;



entity ir is
    Port (
        data_in   : in  STD_LOGIC_VECTOR(15 downto 0);
        ir_ld        : in  STD_LOGIC;
        clk : in std_logic;
        data_out  : out STD_LOGIC_VECTOR(11 downto 0);
        opcode  : out STD_LOGIC_VECTOR(3 downto 0)
    );
end ir;



architecture Behavioral_IR of ir is

    signal data : STD_LOGIC_VECTOR(15 downto 0) := (others => '0');

begin

process(clk)

    begin
        if rising_edge(clk) then
            if ir_ld = '1' then
                data <= data_in;
            end if;
        end if;
    end process;

       opcode <= data(15 downto 12);

       data_out <= data(11 downto 0);

end Behavioral_IR;

src/oe.vhd
library IEEE;
use IEEE.std_logic_1164.all;

entity oe is
    port (
        data_in : in std_logic_vector(15 downto 0);
        clk : in std_logic;
        en : in std_logic;
        data_out : out std_logic_vector(15 downto 0)
    );
end entity oe;

architecture rtl of oe is

begin

    process(clk)
    begin
        if rising_edge(clk) then
            if en = '1' then
                data_out <= data_in;
            else
                data_out <= (others => 'Z');
            end if;
        end if;
    end process;


end architecture rtl;

src/alu.vhd
library IEEE;

use IEEE.STD_LOGIC_1164.ALL;

use IEEE.NUMERIC_STD.ALL;

entity alu is
    port (
        A : in std_logic_vector(15 downto 0);
        B : in std_logic_vector(15 downto 0);
        clk : in std_logic;
        alufs : in std_logic_vector(3 downto 0);
        S : out std_logic_vector(15 downto 0)
    );
end entity alu;

architecture rtl of alu is

begin
    S <= B when alufs = "0000" else
    std_logic_vector(unsigned(B) + 1) when alufs = "0001" else
    std_logic_vector(unsigned(A) + unsigned(B)) when alufs = "0010" else
    std_logic_vector(unsigned(A) - unsigned(B)) when alufs = "0011" else
    (others => '0');
end architecture rtl;

src/acc.vhd
library IEEE;

use IEEE.STD_LOGIC_1164.ALL;

use IEEE.NUMERIC_STD.ALL;

entity acc is
    port (
        data_in : in std_logic_vector(15 downto 0);
        acc_ld : in std_logic;
        clk : in std_logic;
        data_out : out std_logic_vector(15 downto 0);
        accZ : out std_logic;
        acc15 : out std_logic
    );
end entity acc;

architecture accB of acc is
    signal accumulator : std_logic_vector(15 downto 0);

begin
    process(clk, acc_ld, data_in)
    begin
        if rising_edge(clk) then
            if acc_ld = '1' then
                accumulator <= data_in;
            end if;
        end if;
    end process;

    data_out <= accumulator;
    accZ <= '1' when accumulator = X"0000" else '0';
    acc15 <= '1' when accumulator >= X"0000" else '0';

end architecture accB;

src/2bitmux.vhd
library IEEE;

use IEEE.STD_LOGIC_1164.ALL;

use IEEE.NUMERIC_STD.ALL;

entity memValMux is
    Port (
        A : in STD_LOGIC_VECTOR(15 downto 0); -- bus de donnees
        B : in STD_LOGIC_VECTOR(11 downto 0); -- bus d'addresse
        sel : in STD_LOGIC;
        s : out STD_LOGIC_VECTOR(15 downto 0)
    );
end memValMux;

architecture behavioralMux of memValMux is

begin
    process(A, B, sel)
    begin
        if sel = '0' then
            s <= A;
        else
            s(11 downto 0) <= B;
        end if;
    end process;

end architecture behavioralMux;

src/memory_block.vhd
library IEEE;

use IEEE.STD_LOGIC_1164.ALL;

use IEEE.NUMERIC_STD.ALL;



entity mem_block is
    Port (
        reset   : in  STD_LOGIC;                      -- Réinitialisation
        clk : in std_logic;
        RnW     : in  STD_LOGIC;                      -- Lecture/Écriture
        addr    : in  STD_LOGIC_VECTOR(11 downto 0);  -- Bus d'adresses (12 bits)
        data : inout  STD_LOGIC_VECTOR(15 downto 0)  -- Données d'entrée (16 bits)
    );
end mem_block;



architecture Behavioral_mem of mem_block is

    -- Déclaration de la mémoire : 4096 mots (2^12 adresses), 16 bits chacun

    type memory_array is array (0 to 4095) of STD_LOGIC_VECTOR(15 downto 0);

    signal memory : memory_array;
    signal data_in : std_logic_vector(15 downto 0);
    signal data_out : std_logic_vector(15 downto 0);

begin

    process(reset, clk)

    begin

        if reset = '1' then
         memory <= (
	    	      0    => X"0100",  -- LDA @100h (opcode 0, adresse 0100h)

	    	      1    => X"2101",  -- ADD @101h (opcode 0010, adresse 0101h)

	    	      2    => X"6005",  -- JNE  @004h (opcode 0110, adresse 0005h)

	    	      3    => X"3100",  -- SUB @100h (opcode 0011, adresse 0100h)

	    	      4    => X"3100",  -- SUB @100h

	    	      5    => X"2100",  -- ADD @100h

	    	      6    => X"7000",  -- STP  (Stop)


	    	      256  => X"1111",  -- Donnée aléatoire à l'adresse 100h

	    	      257  => X"2222",  -- Donnée aléatoire à l'adresse 101h

	    	      others => (others => '0') -- Initialisation des autres adresses à 0
	    	      );

        elsif rising_edge(clk) then
            if RnW = '0' then  -- Mode écriture
                memory(to_integer(unsigned(addr))) <= data_in;
            else  -- Mode lecture
                data_out <= memory(to_integer(unsigned(addr)));
            end if;
        end if;
    end process;
    data <= data_out when RnW = '1' else data_in;
end Behavioral_mem;

src/sequencer.vhd
library IEEE;

use IEEE.STD_LOGIC_1164.ALL;



entity sequencer is

    Port (
        clk    : in  std_logic;
        reset  : in  std_logic;
        opcode : in  std_logic_vector(3 downto 0);
        accZ   : in  std_logic;
        acc15  : in  std_logic;
        selA   : out std_logic;
        selB   : out std_logic;
        RnW   : out std_logic;
        pc_inc : out std_logic;
        pc_ld  : out std_logic;
        ir_ld  : out std_logic;
        acc_ld : out std_logic;
        acc_oe : out std_logic;
        alufs : out std_logic_vector(3 downto 0)
    );

end sequencer;





architecture structural_seq of sequencer is
    type state_type is (fetch,decode, execute, halt, rst);
    signal curr_state, next_state : state_type := fetch;
begin
    state_reg:process(clk, reset)
    begin
        if reset = '1' then
            curr_state <= rst;
        elsif rising_edge(clk) then
            curr_state <= next_state;
        end if;
    end process;

    next_state <=
        halt when (curr_state = decode and opcode = "0111") else
        execute when (curr_state = decode) else
        decode when (curr_state = fetch) else
        fetch when (curr_state = execute or curr_state = rst) else
        rst when reset = '1' else halt;

    output_logic: process(curr_state, opcode, accZ, acc15)
    begin
        selA <= '0';
        selB <= '0';
        RnW <= '1';
        pc_ld <= '0';
        pc_inc <= '0';
        ir_ld <= '0';
        acc_ld <= '0';
        acc_oe <= '0';
        alufs <= "0000";
        case curr_state is
            when fetch =>
                ir_ld <= '1';
            when decode =>
                case opcode is
                    when "0000" =>
                        pc_inc <= '1';
                        selB <= '1';
                        selA <= '1';
                    when "0001" =>
                        RnW <= '0';
                        selA <= '1';
                        pc_inc <= '1';
                        acc_oe <= '1';
                    when "0010" =>
                        selA <= '1';
                        pc_inc <= '1';
                        selB <= '1';
                    when "0011" =>
                        selA <= '1';
                        pc_inc <= '1';
                        selB <= '1';
                    when "0100" =>
                        selB <= '0';
                        pc_ld <= '1';
                    when "0101" =>
                        if acc15 = '1' then
                            selB <= '0';
                            pc_ld <= '1';
                        end if;
                    when "0110" =>
                        if accZ = '0' then
                            selB <= '0';
                            pc_ld <= '1';
                        end if;
                    when "0111" =>
                        selA <= '0';
                        selB <= '0';
                        RnW <= '0';
                        ir_ld <= '0';
                        acc_ld <= '0';
                        acc_oe <= '0';
                        alufs <= "0000";
                    when others => null;
                    end case;
            when execute =>
                case opcode is
                    when "0000" =>
                        acc_ld <= '1';
                    when "0001" =>
                        acc_ld <= '1';
                    when "0010" =>
                        acc_ld <= '1';
                        alufs <= "0010";
                    when "0011" =>
                        alufs <= "0001";
                        acc_ld <= '1';
                    when others => null;
                    end case;
            when halt => null;
            when rst => null;
            when others => null;
        end case;
    end process;
end structural_seq;

src/mpu.vhd
library IEEE;
use IEEE.STD_LOGIC_1164.ALL;

entity mpu is
    port (
        clk : in std_logic;
        reset: in std_logic
    );
end entity mpu;

architecture rtl of mpu is

    component sequencer is
    Port (
        clk    : in  std_logic;
        reset  : in  std_logic;
        opcode : in  std_logic_vector(3 downto 0);
        accZ   : in  std_logic;
        acc15  : in  std_logic;
        selA   : out std_logic;
        selB   : out std_logic;
        RnW   : out std_logic;
        pc_inc : out std_logic;
        pc_ld  : out std_logic;
        ir_ld  : out std_logic;
        acc_ld : out std_logic;
        acc_oe : out std_logic;
        alufs : out std_logic_vector(3 downto 0)
    );
    end component;
    component memValMux is
    Port (
        A : in STD_LOGIC_VECTOR(15 downto 0); -- bus de donnees
        B : in STD_LOGIC_VECTOR(11 downto 0); -- bus d'addresse
        sel : in STD_LOGIC;
        s : out STD_LOGIC_VECTOR(15 downto 0)
    );
    end component;
    component acc is
    port (
        data_in : in std_logic_vector(15 downto 0);
        acc_ld : in std_logic;
        clk : in std_logic;
        data_out : out std_logic_vector(15 downto 0);
        accZ : out std_logic;
        acc15 : out std_logic
    );
    end component;
    component alu is
    port (
        A : in std_logic_vector(15 downto 0);
        B : in std_logic_vector(15 downto 0);
        clk : in std_logic;
        alufs : in std_logic_vector(3 downto 0);
        S : out std_logic_vector(15 downto 0)
    );
    end component;
    component ir is
    Port (
        data_in   : in  STD_LOGIC_VECTOR(15 downto 0);
        ir_ld        : in  STD_LOGIC;
        clk : in std_logic;
        data_out  : out STD_LOGIC_VECTOR(11 downto 0);
        opcode  : out STD_LOGIC_VECTOR(3 downto 0)
    );
    end component;
    component mem_block is
    Port (
        reset   : in  STD_LOGIC;                      -- Réinitialisation
        RnW     : in  STD_LOGIC;                      -- Lecture/Écriture
        clk : in std_logic;
        addr    : in  STD_LOGIC_VECTOR(11 downto 0);  -- Bus d'adresses (12 bits)
        data : inout std_logic_vector(15 downto 0)
    );
    end component;
    component oe is
    port (
        data_in : in std_logic_vector(15 downto 0);
        en : in std_logic;
        clk : in std_logic;
        data_out : out std_logic_vector(15 downto 0)
    );
    end component;

    component pc is
    Port (
        data_in   : in  STD_LOGIC_VECTOR(15 downto 0);
        pc_ld        : in  STD_LOGIC;
        pc_inc : in std_logic;
        clk : in std_logic;
        reset : in std_logic;
        data_out  : out STD_LOGIC_VECTOR(11 downto 0)
    );
    end component;
    component pcIrMux is
    Port (
        A : in STD_LOGIC_VECTOR(11 downto 0); -- pc
        B : in STD_LOGIC_VECTOR(11 downto 0); -- ir
        sel : in STD_LOGIC;
        s : out STD_LOGIC_VECTOR(11 downto 0)
    );
    end component;

    signal selA, selB, RnW, pc_ld,pc_inc, ir_ld, acc_ld, acc_oe, accZ, acc15 : std_logic;
    signal opcode, alufs : std_logic_vector(3 downto 0);
    signal alu_in1, alu_in2, alu_out: std_logic_vector(15 downto 0);
    signal ir_out, pc_out : std_logic_vector(11 downto 0);
    signal memBus : std_logic_vector(15 downto 0);
    signal addressBus : std_logic_vector(11 downto 0);

begin
sequencer_inst: sequencer
 port map(
    clk => clk,
    reset => reset,
    opcode => opcode,
    accZ => accZ,
    acc15 => acc15,
    selA => selA,
    selB => selB,
    RnW => RnW,
    pc_inc => pc_inc,
    pc_ld => pc_ld,
    ir_ld => ir_ld,
    acc_ld => acc_ld,
    acc_oe => acc_oe,
    alufs => alufs
);


mem_block_inst: mem_block
 port map(
    reset => reset,
    RnW => RnW,
    clk => clk,
    addr => addressBus,
    data => memBus
);

memValMux_inst: memValMux
 port map(
    A => memBus,
    B => addressBus,
    sel => selB,
    s => alu_in2
);

acc_inst: acc
 port map(
    data_in => alu_out,
    acc_ld => acc_ld,
    data_out => alu_in1,
    clk => clk,
    accZ => accZ,
    acc15 => acc15
);

alu_inst: alu
 port map(
    A => alu_in1,
    B => alu_in2,
    clk => clk,
    alufs => alufs,
    S => alu_out
);

oe_inst: oe
 port map(
    data_in => alu_in1,
    en => acc_oe,
    clk => clk,
    data_out => memBus
);
ir_inst: ir
 port map(
    data_in => memBus,
    ir_ld => ir_ld,
    clk => clk,
    data_out => ir_out,
    opcode => opcode
);

pc_inst: pc
 port map(
    data_in => alu_out,
    reset => reset,
    clk => clk,
    pc_ld => pc_ld,
    pc_inc => pc_inc,
    data_out => pc_out
);

pcIrMux_inst: pcIrMux
 port map(
    A => pc_out,
    B => ir_out,
    sel => selA,
    s => addressBus
);

end architecture rtl;

testbench/mpu_tb.vhd
library IEEE;
use IEEE.std_logic_1164.all;
use IEEE.numeric_std.all;

entity mpu_tb is
end entity mpu_tb;

architecture testbench of mpu_tb is
    component mpu is
    port (
        clk : in std_logic;
        reset: in std_logic
    );
    end component;
    signal clk : std_logic := '0';
    signal reset : std_logic := '0';

    constant clk_period : time := 10 ns;
begin

clk_process : process
begin
    while true loop
        clk <= '0';
        wait for clk_period / 2;
        clk <= '1';
        wait for clk_period / 2;
    end loop;
end process;

mpu_inst: mpu
 port map(
    clk => clk,
    reset => reset
);

sim_proc : process
begin
    wait for clk_period;
    reset <= '0';
    wait for 1000 ns;
    assert false report "Simulation" severity failure;
end process;

end architecture testbench;

work/mpu_tb.vcd
$date
  Sun May  4 20:14:29 2025
$end
$version
  GHDL v0
$end
$timescale
  1 fs
$end
$scope module standard $end
$upscope $end
$scope module textio $end
$upscope $end
$scope module std_logic_1164 $end
$upscope $end
$scope module numeric_std $end
$upscope $end
$scope module mpu_tb $end
$var reg 1 ! clk $end
$var reg 1 " reset $end
$scope module mpu_inst $end
$var reg 1 # clk $end
$var reg 1 $ reset $end
$var reg 1 % sela $end
$var reg 1 & selb $end
$var reg 1 ' rnw $end
$var reg 1 ( pc_ld $end
$var reg 1 ) pc_inc $end
$var reg 1 * ir_ld $end
$var reg 1 + acc_ld $end
$var reg 1 , acc_oe $end
$var reg 1 - accz $end
$var reg 1 . acc15 $end
$var reg 4 / opcode[3:0] $end
$var reg 4 0 alufs[3:0] $end
$var reg 16 1 alu_in1[15:0] $end
$var reg 16 2 alu_in2[15:0] $end
$var reg 16 3 alu_out[15:0] $end
$var reg 12 4 ir_out[11:0] $end
$var reg 12 5 pc_out[11:0] $end
$var reg 16 6 membus[15:0] $end
$var reg 12 7 addressbus[11:0] $end
$scope module sequencer_inst $end
$var reg 1 8 clk $end
$var reg 1 9 reset $end
$var reg 4 : opcode[3:0] $end
$var reg 1 ; accz $end
$var reg 1 < acc15 $end
$var reg 1 = sela $end
$var reg 1 > selb $end
$var reg 1 ? rnw $end
$var reg 1 @ pc_inc $end
$var reg 1 A pc_ld $end
$var reg 1 B ir_ld $end
$var reg 1 C acc_ld $end
$var reg 1 D acc_oe $end
$var reg 4 E alufs[3:0] $end
$comment curr_state is not handled $end
$comment next_state is not handled $end
$upscope $end
$scope module mem_block_inst $end
$var reg 1 F reset $end
$var reg 1 G clk $end
$var reg 1 H rnw $end
$var reg 12 I addr[11:0] $end
$var reg 16 J data[15:0] $end
$comment memory is not handled $end
$var reg 16 K data_in[15:0] $end
$var reg 16 L data_out[15:0] $end
$upscope $end
$scope module memvalmux_inst $end
$var reg 16 M a[15:0] $end
$var reg 12 N b[11:0] $end
$var reg 1 O sel $end
$var reg 16 P s[15:0] $end
$upscope $end
$scope module acc_inst $end
$var reg 16 Q data_in[15:0] $end
$var reg 1 R acc_ld $end
$var reg 1 S clk $end
$var reg 16 T data_out[15:0] $end
$var reg 1 U accz $end
$var reg 1 V acc15 $end
$var reg 16 W accumulator[15:0] $end
$upscope $end
$scope module alu_inst $end
$var reg 16 X a[15:0] $end
$var reg 16 Y b[15:0] $end
$var reg 1 Z clk $end
$var reg 4 [ alufs[3:0] $end
$var reg 16 \ s[15:0] $end
$upscope $end
$scope module oe_inst $end
$var reg 16 ] data_in[15:0] $end
$var reg 1 ^ clk $end
$var reg 1 _ en $end
$var reg 16 ` data_out[15:0] $end
$upscope $end
$scope module ir_inst $end
$var reg 16 a data_in[15:0] $end
$var reg 1 b ir_ld $end
$var reg 1 c clk $end
$var reg 12 d data_out[11:0] $end
$var reg 4 e opcode[3:0] $end
$var reg 16 f data[15:0] $end
$upscope $end
$scope module pc_inst $end
$var reg 16 g data_in[15:0] $end
$var reg 1 h clk $end
$var reg 1 i pc_ld $end
$var reg 1 j pc_inc $end
$var reg 1 k reset $end
$var reg 12 l data_out[11:0] $end
$var reg 12 m counter[11:0] $end
$upscope $end
$scope module pcirmux_inst $end
$var reg 12 n a[11:0] $end
$var reg 12 o b[11:0] $end
$var reg 1 p sel $end
$var reg 12 q s[11:0] $end
$upscope $end
$upscope $end
$upscope $end
$enddefinitions $end
#0
0!
1"
0#
1$
0%
0&
1'
0(
0)
0*
0+
0,
0-
0.
b0000 /
b0000 0
bUUUUUUUUUUUUUUUU 1
bUUUUUUUUUUUUUUUU 2
bUUUUUUUUUUUUUUUU 3
b000000000000 4
b000000000000 5
bUUUUUUUUUUUUUUUU 6
b000000000000 7
08
19
b0000 :
0;
0<
0=
0>
1?
0@
0A
0B
0C
0D
b0000 E
1F
0G
1H
b000000000000 I
bUUUUUUUUUUUUUUUU J
bUUUUUUUUUUUUUUUU K
bUUUUUUUUUUUUUUUU L
bUUUUUUUUUUUUUUUU M
b000000000000 N
0O
bUUUUUUUUUUUUUUUU P
bUUUUUUUUUUUUUUUU Q
0R
0S
bUUUUUUUUUUUUUUUU T
0U
0V
bUUUUUUUUUUUUUUUU W
bUUUUUUUUUUUUUUUU X
bUUUUUUUUUUUUUUUU Y
0Z
b0000 [
bUUUUUUUUUUUUUUUU \
bUUUUUUUUUUUUUUUU ]
0^
0_
bUUUUUUUUUUUUUUUU `
bUUUUUUUUUUUUUUUU a
0b
0c
b000000000000 d
b0000 e
b0000000000000000 f
bUUUUUUUUUUUUUUUU g
0h
0i
0j
1k
b000000000000 l
b000000000000 m
b000000000000 n
b000000000000 o
0p
b000000000000 q
#10000000
1!
1#
18
1G
1S
1Z
1^
bUUUUUUUUUUUUUUUU `
1c
1h
#20000000
0!
0#
08
0G
0S
0Z
0^
0c
0h
#25000000
0"
0$
09
0F
0k
#30000000
1!
1#
1*
b0000000100000000 2
b0000000100000000 3
b0000000100000000 6
18
1B
1G
b0000000100000000 J
b0000000100000000 L
b0000000100000000 M
b0000000100000000 P
b0000000100000000 Q
1S
b0000000100000000 Y
1Z
b0000000100000000 \
1^
b0000000100000000 `
b0000000100000000 a
1b
1c
b0000000100000000 g
1h
#40000000
0!
0#
08
0G
0S
0Z
0^
0c
0h
#50000000
1!
1#
1%
1&
1)
0*
b0000000100000000 2
b0000000100000000 3
b000100000000 4
b000100000000 7
18
1=
1>
1@
0B
1G
b000100000000 I
b000100000000 N
1O
b0000000100000000 P
b0000000100000000 Q
1S
b0000000100000000 Y
1Z
b0000000100000000 \
1^
b0000000100000000 `
0b
1c
b000100000000 d
b0000000100000000 f
b0000000100000000 g
1h
1j
b000100000000 o
1p
b000100000000 q
#60000000
0!
0#
08
0G
0S
0Z
0^
0c
0h
#70000000
1!
1#
0%
0&
0)
1+
b0001000100010001 2
b0001000100010001 3
b000000000001 5
b0001000100010001 6
b000000000001 7
18
0=
0>
0@
1C
1G
b000000000001 I
b0001000100010001 J
b0001000100010001 L
b0001000100010001 M
b000000000001 N
0O
b0001000100010001 P
b0001000100010001 Q
1R
1S
b0001000100010001 Y
1Z
b0001000100010001 \
1^
b0001000100010001 `
b0001000100010001 a
1c
b0001000100010001 g
1h
0j
b000000000001 l
b000000000001 m
b000000000001 n
0p
b000000000001 q
#80000000
0!
0#
08
0G
0S
0Z
0^
0c
0h
#90000000
1!
1#
1*
0+
1.
b0001000100010001 1
b0010000100000001 2
b0010000100000001 3
b0010000100000001 6
18
1<
1B
0C
1G
b0010000100000001 J
b0010000100000001 L
b0010000100000001 M
b0010000100000001 P
b0010000100000001 Q
0R
1S
b0001000100010001 T
1V
b0001000100010001 W
b0001000100010001 X
b0010000100000001 Y
1Z
b0010000100000001 \
b0001000100010001 ]
1^
b0010000100000001 `
b0010000100000001 a
1b
1c
b0010000100000001 g
1h
#100000000
0!
0#
08
0G
0S
0Z
0^
0c
0h
#110000000
1!
1#
1%
1&
1)
0*
b0010 /
b0010000100000001 2
b0010000100000001 3
b000100000001 4
b000100000001 7
18
b0010 :
1=
1>
1@
0B
1G
b000100000001 I
b000100000001 N
1O
b0010000100000001 P
b0010000100000001 Q
1S
b0010000100000001 Y
1Z
b0010000100000001 \
1^
b0010000100000001 `
0b
1c
b000100000001 d
b0010 e
b0010000100000001 f
b0010000100000001 g
1h
1j
b000100000001 o
1p
b000100000001 q
#120000000
0!
0#
08
0G
0S
0Z
0^
0c
0h
#130000000
1!
1#
0%
0&
0)
1+
b0010 0
b0010001000100010 2
b0011001100110011 3
b000000000010 5
b0010001000100010 6
b000000000010 7
18
0=
0>
0@
1C
b0010 E
1G
b000000000010 I
b0010001000100010 J
b0010001000100010 L
b0010001000100010 M
b000000000010 N
0O
b0010001000100010 P
b0011001100110011 Q
1R
1S
b0010001000100010 Y
1Z
b0010 [
b0011001100110011 \
1^
b0010001000100010 `
b0010001000100010 a
1c
b0011001100110011 g
1h
0j
b000000000010 l
b000000000010 m
b000000000010 n
0p
b000000000010 q
#140000000
0!
0#
08
0G
0S
0Z
0^
0c
0h
#150000000
1!
1#
1*
0+
b0000 0
b0011001100110011 1
b0110000000000101 2
b0110000000000101 3
b0110000000000101 6
18
1B
0C
b0000 E
1G
b0110000000000101 J
b0110000000000101 L
b0110000000000101 M
b0110000000000101 P
b0110000000000101 Q
0R
1S
b0011001100110011 T
b0011001100110011 W
b0011001100110011 X
b0110000000000101 Y
1Z
b0000 [
b0110000000000101 \
b0011001100110011 ]
1^
b0110000000000101 `
b0110000000000101 a
1b
1c
b0110000000000101 g
1h
#160000000
0!
0#
08
0G
0S
0Z
0^
0c
0h
#170000000
1!
1#
0%
0&
1(
0)
0*
b0110 /
b0110000000000101 2
b0110000000000101 3
b000000000101 4
b000000000010 7
18
b0110 :
0=
0>
0@
1A
0B
1G
b000000000010 I
b000000000010 N
0O
b0110000000000101 P
b0110000000000101 Q
1S
b0110000000000101 Y
1Z
b0110000000000101 \
1^
b0110000000000101 `
0b
1c
b000000000101 d
b0110 e
b0110000000000101 f
b0110000000000101 g
1h
1i
0j
b000000000101 o
0p
b000000000010 q
#180000000
0!
0#
08
0G
0S
0Z
0^
0c
0h
#190000000
1!
1#
0(
b000000000101 5
b000000000101 7
18
0A
1G
b000000000101 I
b000000000101 N
1S
1Z
1^
b0110000000000101 `
1c
1h
0i
b000000000101 l
b000000000101 m
b000000000101 n
b000000000101 q
#200000000
0!
0#
08
0G
0S
0Z
0^
0c
0h
#210000000
1!
1#
1*
b0010000100000000 2
b0010000100000000 3
b0010000100000000 6
18
1B
1G
b0010000100000000 J
b0010000100000000 L
b0010000100000000 M
b0010000100000000 P
b0010000100000000 Q
1S
b0010000100000000 Y
1Z
b0010000100000000 \
1^
b0010000100000000 `
b0010000100000000 a
1b
1c
b0010000100000000 g
1h
#220000000
0!
0#
08
0G
0S
0Z
0^
0c
0h
#230000000
1!
1#
1%
1&
0(
1)
0*
b0010 /
b0010000100000000 2
b0010000100000000 3
b000100000000 4
b000100000000 7
18
b0010 :
1=
1>
1@
0A
0B
1G
b000100000000 I
b000100000000 N
1O
b0010000100000000 P
b0010000100000000 Q
1S
b0010000100000000 Y
1Z
b0010000100000000 \
1^
b0010000100000000 `
0b
1c
b000100000000 d
b0010 e
b0010000100000000 f
b0010000100000000 g
1h
0i
1j
b000100000000 o
1p
b000100000000 q
#240000000
0!
0#
08
0G
0S
0Z
0^
0c
0h
#250000000
1!
1#
0%
0&
0)
1+
b0010 0
b0001000100010001 2
b0100010001000100 3
b000000000110 5
b0001000100010001 6
b000000000110 7
18
0=
0>
0@
1C
b0010 E
1G
b000000000110 I
b0001000100010001 J
b0001000100010001 L
b0001000100010001 M
b000000000110 N
0O
b0001000100010001 P
b0100010001000100 Q
1R
1S
b0001000100010001 Y
1Z
b0010 [
b0100010001000100 \
1^
b0001000100010001 `
b0001000100010001 a
1c
b0100010001000100 g
1h
0j
b000000000110 l
b000000000110 m
b000000000110 n
0p
b000000000110 q
#260000000
0!
0#
08
0G
0S
0Z
0^
0c
0h
#270000000
1!
1#
1*
0+
b0000 0
b0100010001000100 1
b0111000000000000 2
b0111000000000000 3
b0111000000000000 6
18
1B
0C
b0000 E
1G
b0111000000000000 J
b0111000000000000 L
b0111000000000000 M
b0111000000000000 P
b0111000000000000 Q
0R
1S
b0100010001000100 T
b0100010001000100 W
b0100010001000100 X
b0111000000000000 Y
1Z
b0000 [
b0111000000000000 \
b0100010001000100 ]
1^
b0111000000000000 `
b0111000000000000 a
1b
1c
b0111000000000000 g
1h
#280000000
0!
0#
08
0G
0S
0Z
0^
0c
0h
#290000000
1!
1#
0%
0&
0'
0)
0*
b0111 /
bUUUUUUUUUUUUUUUU 2
bUUUUUUUUUUUUUUUU 3
b000000000000 4
bUUUUUUUUUUUUUUUU 6
b000000000110 7
18
b0111 :
0=
0>
0?
0@
0B
1G
0H
b000000000110 I
bUUUUUUUUUUUUUUUU J
bUUUUUUUUUUUUUUUU M
b000000000110 N
0O
bUUUUUUUUUUUUUUUU P
bUUUUUUUUUUUUUUUU Q
1S
bUUUUUUUUUUUUUUUU Y
1Z
bUUUUUUUUUUUUUUUU \
1^
bUUUUUUUUUUUUUUUU `
bUUUUUUUUUUUUUUUU a
0b
1c
b000000000000 d
b0111 e
b0111000000000000 f
bUUUUUUUUUUUUUUUU g
1h
0j
b000000000000 o
0p
b000000000110 q
#300000000
0!
0#
08
0G
0S
0Z
0^
0c
0h
#310000000
1!
1#
1'
b0111000000000000 2
b0111000000000000 3
b0111000000000000 6
18
1?
1G
1H
b0111000000000000 J
b0111000000000000 M
b0111000000000000 P
b0111000000000000 Q
1S
b0111000000000000 Y
1Z
b0111000000000000 \
1^
b0111000000000000 `
b0111000000000000 a
1c
b0111000000000000 g
1h
#320000000
0!
0#
08
0G
0S
0Z
0^
0c
0h
#330000000
1!
1#
bUUUUUUUUUUUUUUUU 2
bUUUUUUUUUUUUUUUU 3
bUUUUUUUUUUUUUUUU 6
18
1G
bUUUUUUUUUUUUUUUU J
bUUUUUUUUUUUUUUUU L
bUUUUUUUUUUUUUUUU M
bUUUUUUUUUUUUUUUU P
bUUUUUUUUUUUUUUUU Q
1S
bUUUUUUUUUUUUUUUU Y
1Z
bUUUUUUUUUUUUUUUU \
1^
bUUUUUUUUUUUUUUUU `
bUUUUUUUUUUUUUUUU a
1c
bUUUUUUUUUUUUUUUU g
1h
#340000000
0!
0#
08
0G
0S
0Z
0^
0c
0h
#350000000
1!
1#
18
1G
1S
1Z
1^
bUUUUUUUUUUUUUUUU `
1c
1h
#360000000
0!
0#
08
0G
0S
0Z
0^
0c
0h
#370000000
1!
1#
18
1G
1S
1Z
1^
bUUUUUUUUUUUUUUUU `
1c
1h
#380000000
0!
0#
08
0G
0S
0Z
0^
0c
0h
#390000000
1!
1#
18
1G
1S
1Z
1^
bUUUUUUUUUUUUUUUU `
1c
1h
#400000000
0!
0#
08
0G
0S
0Z
0^
0c
0h
#410000000
1!
1#
18
1G
1S
1Z
1^
bUUUUUUUUUUUUUUUU `
1c
1h
#420000000
0!
0#
08
0G
0S
0Z
0^
0c
0h
#430000000
1!
1#
18
1G
1S
1Z
1^
bUUUUUUUUUUUUUUUU `
1c
1h
#440000000
0!
0#
08
0G
0S
0Z
0^
0c
0h
#450000000
1!
1#
18
1G
1S
1Z
1^
bUUUUUUUUUUUUUUUU `
1c
1h
#460000000
0!
0#
08
0G
0S
0Z
0^
0c
0h
#470000000
1!
1#
18
1G
1S
1Z
1^
bUUUUUUUUUUUUUUUU `
1c
1h
#480000000
0!
0#
08
0G
0S
0Z
0^
0c
0h
#490000000
1!
1#
18
1G
1S
1Z
1^
bUUUUUUUUUUUUUUUU `
1c
1h
#500000000
0!
0#
08
0G
0S
0Z
0^
0c
0h
#510000000
1!
1#
18
1G
1S
1Z
1^
bUUUUUUUUUUUUUUUU `
1c
1h
#520000000
0!
0#
08
0G
0S
0Z
0^
0c
0h
#530000000
1!
1#
18
1G
1S
1Z
1^
bUUUUUUUUUUUUUUUU `
1c
1h
#540000000
0!
0#
08
0G
0S
0Z
0^
0c
0h
#550000000
1!
1#
18
1G
1S
1Z
1^
bUUUUUUUUUUUUUUUU `
1c
1h
#560000000
0!
0#
08
0G
0S
0Z
0^
0c
0h
#570000000
1!
1#
18
1G
1S
1Z
1^
bUUUUUUUUUUUUUUUU `
1c
1h
#580000000
0!
0#
08
0G
0S
0Z
0^
0c
0h
#590000000
1!
1#
18
1G
1S
1Z
1^
bUUUUUUUUUUUUUUUU `
1c
1h
#600000000
0!
0#
08
0G
0S
0Z
0^
0c
0h
#610000000
1!
1#
18
1G
1S
1Z
1^
bUUUUUUUUUUUUUUUU `
1c
1h
#620000000
0!
0#
08
0G
0S
0Z
0^
0c
0h
#630000000
1!
1#
18
1G
1S
1Z
1^
bUUUUUUUUUUUUUUUU `
1c
1h
