src/pcIrMux.vhd
library IEEE;
use IEEE.std_logic_1164.all;

entity pcIrMux is
    Port (
        A : in STD_LOGIC_VECTOR(11 downto 0); -- pc
        B : in STD_LOGIC_VECTOR(11 downto 0); -- ir
        sel : in STD_LOGIC;
        s : out STD_LOGIC_VECTOR(11 downto 0)
    );
end pcIrMux;

architecture behavioralMux of pcIrMux is

begin
    process(A, B, sel)
    begin
        if sel = '0' then
            s <= A;
        else
            s <= B;
        end if;
    end process;

end architecture behavioralMux;

src/pc.vhd
library IEEE;

use IEEE.STD_LOGIC_1164.ALL;

use IEEE.NUMERIC_STD.ALL;



entity pc is
    Port (
        data_in   : in  STD_LOGIC_VECTOR(15 downto 0);
        pc_ld        : in  STD_LOGIC;
        clk : in std_logic;
        data_out  : out STD_LOGIC_VECTOR(11 downto 0)
    );
end pc;



architecture Behavioral_PC of pc is

    signal data : STD_LOGIC_VECTOR(15 downto 0) := (others => '0');

begin

process(pc_ld, data_in)

    begin
        if rising_edge(clk) then
            if pc_ld = '1' then

                data <= data_in;

            end if;
        end if;

    end process;

       data_out <= data(11 downto 0);

end Behavioral_PC;

src/ir.vhd
library IEEE;

use IEEE.STD_LOGIC_1164.ALL;

use IEEE.NUMERIC_STD.ALL;



entity ir is
    Port (
        data_in   : in  STD_LOGIC_VECTOR(15 downto 0);
        ir_ld        : in  STD_LOGIC;
        data_out  : out STD_LOGIC_VECTOR(11 downto 0);
        opcode  : out STD_LOGIC_VECTOR(3 downto 0)
    );
end ir;



architecture Behavioral_IR of ir is

    signal data : STD_LOGIC_VECTOR(15 downto 0) := (others => '0');

begin

process(ir_ld, data_in)

    begin
        if ir_ld = '1' then
            data <= data_in;
        end if;
    end process;

       opcode <= data(15 downto 12);

       data_out <= data(11 downto 0);

end Behavioral_IR;

src/oe.vhd
library IEEE;
use IEEE.std_logic_1164.all;

entity oe is
    port (
        data_in : in std_logic_vector(15 downto 0);
        en : in std_logic;
        data_out : out std_logic_vector(15 downto 0)
    );
end entity oe;

architecture rtl of oe is

begin

    process(data_in, en)
    begin
        if en = '1' then
            data_out <= data_in;
        end if;
    end process;


end architecture rtl;

src/alu.vhd
library IEEE;

use IEEE.STD_LOGIC_1164.ALL;

use IEEE.NUMERIC_STD.ALL;

entity alu is
    port (
        A : in std_logic_vector(15 downto 0);
        B : in std_logic_vector(15 downto 0);
        alufs : in std_logic_vector(3 downto 0);
        S : out std_logic_vector(15 downto 0)
    );
end entity alu;

architecture rtl of alu is

begin

    process (A, B, alufs)
    begin
        case alufs is
            when X"0" => S <= B;
            when X"1" => S <= std_logic_vector(unsigned(A) - unsigned(B));
            when X"2" => S <= std_logic_vector(unsigned(A) + unsigned(B));
            when X"3" => S <= std_logic_vector(unsigned(B) + 1);
            when others => S <= ( others => '0' );
        end case;
    end process;
end architecture rtl;

src/acc.vhd
library IEEE;

use IEEE.STD_LOGIC_1164.ALL;

use IEEE.NUMERIC_STD.ALL;

entity acc is
    port (
        data_in : in std_logic_vector(15 downto 0);
        acc_ld : in std_logic;
        clk : in std_logic;
        data_out : out std_logic_vector(15 downto 0);
        accZ : out std_logic;
        acc15 : out std_logic
    );
end entity acc;

architecture accB of acc is
    signal accumulator : std_logic_vector(15 downto 0);

begin
    process(clk, acc_ld, data_in)
    begin
        if rising_edge(clk) then
            if acc_ld = '1' then
                accumulator <= data_in;
            end if;
        end if;
    end process;

    data_out <= accumulator;
    accZ <= '1' when accumulator = X"0000" else '0';
    acc15 <= '1' when accumulator >= X"0000" else '0';

end architecture accB;

src/2bitmux.vhd
library IEEE;

use IEEE.STD_LOGIC_1164.ALL;

use IEEE.NUMERIC_STD.ALL;

entity memValMux is
    Port (
        A : in STD_LOGIC_VECTOR(15 downto 0); -- bus de donnees
        B : in STD_LOGIC_VECTOR(11 downto 0); -- bus d'addresse
        sel : in STD_LOGIC;
        s : out STD_LOGIC_VECTOR(15 downto 0)
    );
end memValMux;

architecture behavioralMux of memValMux is

begin
    process(A, B, sel)
    begin
        if sel = '0' then
            s <= A;
        else
            s(11 downto 0) <= B;
        end if;
    end process;

end architecture behavioralMux;

src/memory_block.vhd
library IEEE;

use IEEE.STD_LOGIC_1164.ALL;

use IEEE.NUMERIC_STD.ALL;



entity mem_block is
    Port (
        clk     : in  STD_LOGIC;                      -- Horloge
        reset   : in  STD_LOGIC;                      -- Réinitialisation
        RnW     : in  STD_LOGIC;                      -- Lecture/Écriture
        addr    : in  STD_LOGIC_VECTOR(11 downto 0);  -- Bus d'adresses (12 bits)
        data_in : in  STD_LOGIC_VECTOR(15 downto 0);  -- Données d'entrée (16 bits)
        data_out: out STD_LOGIC_VECTOR(15 downto 0)   -- Données de sortie (16 bits)
    );
end mem_block;



architecture Behavioral_mem of mem_block is

    -- Déclaration de la mémoire : 4096 mots (2^12 adresses), 16 bits chacun

    type memory_array is array (0 to 4095) of STD_LOGIC_VECTOR(15 downto 0);

    signal memory : memory_array := (

        -- Instructions principales

        0    => X"2100",  -- LDA @100h (opcode 21, adresse 0100h)

        1    => X"3101",  -- ADD @101h (opcode 31, adresse 0101h)

        2    => X"5404",  -- JNE  @004h (opcode 54, adresse 0004h)

        3    => X"4100",  -- SUB @100h (opcode 41, adresse 0100h)

        4    => X"4100",  -- SUB @100h

        5    => X"3100",  -- ADD @100h

        6    => X"0000",  -- STP  (Stop)



        -- Données aléatoires

        256  => X"ABCD",  -- Donnée aléatoire à l'adresse 100h

        257  => X"1234",  -- Donnée aléatoire à l'adresse 101h

        258  => X"5678",  -- Donnée aléatoire

        259  => X"9ABC",  -- Donnée aléatoire

        260  => X"DEFA",  -- Donnée aléatoire

        261  => X"1357",  -- Donnée aléatoire

        262  => X"2468",  -- Donnée aléatoire

        263  => X"FACE",  -- Donnée aléatoire

        264  => X"BEAD",  -- Donnée aléatoire

        265  => X"C0DE",  -- Donnée aléatoire

        others => (others => '0') -- Initialisation des autres adresses à 0

    );

begin

    process(clk, reset)

    begin

        if reset = '1' then
            -- Réinitialisation de la mémoire
            memory <= (others => (others => '0'));
            data_out <= (others => '0');
        elsif rising_edge(clk) then

            if RnW = '0' then  -- Mode écriture
                memory(to_integer(unsigned(addr))) <= data_in;
            else  -- Mode lecture
                data_out <= memory(to_integer(unsigned(addr)));
            end if;

        end if;

    end process;

end Behavioral_mem;

src/sequencer.vhd
library IEEE;

use IEEE.STD_LOGIC_1164.ALL;



entity sequencer is

    Port (
        clk    : in  std_logic;
        reset  : in  std_logic;
        opcode : in  std_logic_vector(3 downto 0);
        accZ   : in  std_logic;
        acc15  : in  std_logic;
        selA   : out std_logic;
        selB   : out std_logic;
        RnW   : out std_logic;
        pc_ld  : out std_logic;
        ir_ld  : out std_logic;
        acc_ld : out std_logic;
        acc_oe : out std_logic;
        alufs : out std_logic_vector(3 downto 0)
    );

end sequencer;





architecture structural_seq of sequencer is
    signal Q      : std_logic_vector(3 downto 0);

    signal Q_next : std_logic_vector(3 downto 0);
begin



    -- Processus pour l'état présent : registre synchrone

    process(clk, reset)

    begin

        if reset = '1' then

            Q <= "0000";  -- Etat initial

        elsif rising_edge(clk) then

            Q <= Q_next;  -- Mise à jour avec l'état futur

        end if;

    end process;



    -- Logique combinatoire pour l'état futur

    Q_next(0) <= (not Q(3) and not Q(1) and not Q(0) and opcode(2) and opcode(1) and opcode(0)) or

                 (not Q(1) and Q(0) and opcode(2) and not opcode(1) and not opcode(0)) or

                 (not Q(2) and Q(1) and not Q(0) and not opcode(2) and not opcode(1) and opcode(0)) or

                 (not Q(3) and Q(2) and not Q(1)) or

                 (not Q(3) and Q(2) and Q(0)) or

                 (Q(3) and not Q(1) and Q(0)) or

                 (Q(3) and Q(1) and not Q(0));



    Q_next(1) <= (not Q(3) and not Q(1) and Q(0) and opcode(2) and not opcode(1) and not opcode(0)) or

                 (not Q(3) and not Q(1) and Q(0) and not acc15 and accZ and opcode(2) and not opcode(1)) or

                 (not Q(3) and not Q(1) and Q(0) and acc15 and not accZ and opcode(2) and not opcode(0)) or

                 (not Q(3) and Q(0) and not Q(1)) or

                 (not Q(3) and Q(2)) or

                 (Q(2) and not Q(1) and Q(0));



    Q_next(2) <= (not Q(3) and not Q(2) and Q(0) and not acc15) or

                 (not Q(3) and not Q(2) and Q(0) and not opcode(2)) or

                 (not Q(3) and not Q(2) and Q(0) and not accZ and not opcode(1)) or

                 (not Q(3) and not Q(2) and Q(0) and opcode(0)) or

                 (not Q(3) and not Q(2) and Q(0) and accZ and opcode(1)) or

                 (Q(1) and not Q(0) and opcode(1) and not opcode(0)) or

                 (Q(3) and Q(1) and not Q(0)) or

                 (Q(3) and Q(2) and not Q(1) and Q(0)) or

                 (not Q(3) and not Q(2) and Q(1) and not opcode(0)) or

                 (not Q(3) and not Q(2) and Q(1) and opcode(1));



    Q_next(3) <= (not Q(3) and not Q(2) and not Q(1) and not opcode(2)) or

                 (not Q(3) and not Q(2) and not Q(1) and not accZ and opcode(0)) or

                 (not Q(3) and not Q(2) and not Q(1) and opcode(1)) or

                 (not Q(3) and not Q(2) and not Q(1) and acc15 and opcode(0)) or

                 (not Q(3) and Q(2) and Q(1) and not Q(0) and not opcode(0)) or

                 (Q(3) and not Q(2) and Q(1) and not Q(0)) or

                 (Q(3) and Q(2) and not Q(1) and Q(0)) or

                 (not Q(3) and not Q(2) and not Q(1) and not Q(0)) or

                 (not Q(3) and not Q(2) and not Q(0) and not opcode(1) and opcode(0));



    -- Logique combinatoire pour les sorties

    selA    <= (Q(1) and not Q(0)) or Q(2) or Q(3);

    selB    <= Q(2) or Q(3);

    ir_ld   <= (not Q(2) and not Q(1) and Q(0));

    acc_ld  <= (not Q(3) and not Q(2) and Q(1) and not Q(0)) or (Q(3) and Q(2) and not Q(1) and not Q(0));

    acc_oe  <= (Q(3) and Q(2) and not Q(1) and Q(0));

    pc_ld   <= (Q(3) and not Q(2) and Q(1) and Q(0));

    RnW <= (not Q(3)) or (not Q(2)) or (not Q(0)) or Q(1);

    alufs(1) <= Q(1);

    alufs(0) <= (not Q(2)) or (not Q(0));

    alufs(3 downto 2) <= "00";



end structural_seq;

src/mpu.vhd
library IEEE;
use IEEE.STD_LOGIC_1164.ALL;

entity mpu is
    port (
        clk : in std_logic;
        reset: in std_logic
    );
end entity mpu;

architecture rtl of mpu is

    component sequencer is
    Port (
        clk    : in  std_logic;
        reset  : in  std_logic;
        opcode : in  std_logic_vector(3 downto 0);
        accZ   : in  std_logic;
        acc15  : in  std_logic;
        selA   : out std_logic;
        selB   : out std_logic;
        RnW   : out std_logic;
        pc_ld  : out std_logic;
        ir_ld  : out std_logic;
        acc_ld : out std_logic;
        acc_oe : out std_logic;
        alufs : out std_logic_vector(3 downto 0)
    );
    end component;
    component memValMux is
    Port (
        A : in STD_LOGIC_VECTOR(15 downto 0); -- bus de donnees
        B : in STD_LOGIC_VECTOR(11 downto 0); -- bus d'addresse
        sel : in STD_LOGIC;
        s : out STD_LOGIC_VECTOR(15 downto 0)
    );
    end component;
    component acc is
    port (
        data_in : in std_logic_vector(15 downto 0);
        acc_ld : in std_logic;
        clk : in std_logic;
        data_out : out std_logic_vector(15 downto 0);
        accZ : out std_logic;
        acc15 : out std_logic
    );
    end component;
    component alu is
    port (
        A : in std_logic_vector(15 downto 0);
        B : in std_logic_vector(15 downto 0);
        alufs : in std_logic_vector(3 downto 0);
        S : out std_logic_vector(15 downto 0)
    );
    end component;
    component ir is
    Port (
        data_in   : in  STD_LOGIC_VECTOR(15 downto 0);
        ir_ld        : in  STD_LOGIC;
        data_out  : out STD_LOGIC_VECTOR(11 downto 0);
        opcode  : out STD_LOGIC_VECTOR(3 downto 0)
    );
    end component;
    component mem_block is
    Port (
        clk     : in  STD_LOGIC;                      -- Horloge
        reset   : in  STD_LOGIC;                      -- Réinitialisation
        RnW     : in  STD_LOGIC;                      -- Lecture/Écriture
        addr    : in  STD_LOGIC_VECTOR(11 downto 0);  -- Bus d'adresses (12 bits)
        data_in : in  STD_LOGIC_VECTOR(15 downto 0);  -- Données d'entrée (16 bits)
        data_out: out STD_LOGIC_VECTOR(15 downto 0)   -- Données de sortie (16 bits)
    );
    end component;
    component oe is
    port (
        data_in : in std_logic_vector(15 downto 0);
        en : in std_logic;
        data_out : out std_logic_vector(15 downto 0)
    );
    end component;

    component pc is
    Port (
        data_in   : in  STD_LOGIC_VECTOR(15 downto 0);
        pc_ld        : in  STD_LOGIC;
        clk : in std_logic;
        data_out  : out STD_LOGIC_VECTOR(11 downto 0)
    );
    end component;
    component pcIrMux is
    Port (
        A : in STD_LOGIC_VECTOR(11 downto 0); -- pc
        B : in STD_LOGIC_VECTOR(11 downto 0); -- ir
        sel : in STD_LOGIC;
        s : out STD_LOGIC_VECTOR(11 downto 0)
    );
    end component;

    signal selA, selB, RnW, pc_ld, ir_ld, acc_ld, acc_oe, accZ, acc15 : std_logic;
    signal opcode, alufs : std_logic_vector(3 downto 0);
    signal alu_in1, alu_in2, alu_out: std_logic_vector(15 downto 0);
    signal oe_enable_signal : std_logic;
    signal ir_out, pc_out : std_logic_vector(11 downto 0);
    signal memBus : std_logic_vector(15 downto 0);
    signal addressBus : std_logic_vector(11 downto 0);

begin
sequencer_inst: sequencer
 port map(
    clk => clk,
    reset => reset,
    opcode => opcode,
    accZ => accZ,
    acc15 => acc15,
    selA => selA,
    selB => selB,
    RnW => RnW,
    pc_ld => pc_ld,
    ir_ld => ir_ld,
    acc_ld => acc_ld,
    acc_oe => acc_oe,
    alufs => alufs
);

mem_block_inst: mem_block
 port map(
    clk => clk,
    reset => reset,
    RnW => RnW,
    addr => addressBus,
    data_in => memBus,
    data_out => memBus
);

memValMux_inst: memValMux
 port map(
    A => memBus,
    B => addressBus,
    sel => selB,
    s => alu_in2
);

acc_inst: acc
 port map(
    clk => clk,
    data_in => alu_out,
    acc_ld => acc_ld,
    data_out => alu_in1,
    accZ => accZ,
    acc15 => acc15
);

alu_inst: alu
 port map(
    A => alu_in1,
    B => alu_in2,
    alufs => alufs,
    S => alu_out
);

oe_inst: oe
 port map(
    data_in => alu_in1,
    en => oe_enable_signal,
    data_out => memBus
);
ir_inst: ir
 port map(
    data_in => memBus,
    ir_ld => ir_ld,
    data_out => ir_out,
    opcode => opcode
);

pc_inst: pc
 port map(
    clk => clk,
    data_in => alu_out,
    pc_ld => pc_ld,
    data_out => pc_out
);

pcIrMux_inst: pcIrMux
 port map(
    A => pc_out,
    B => ir_out,
    sel => selA,
    s => addressBus
);

end architecture rtl;

testbench/mpu_tb.vhd
library IEEE;
use IEEE.std_logic_1164.all;
use IEEE.numeric_std.all;

entity mpu_tb is
end entity mpu_tb;

architecture testbench of mpu_tb is
    component mpu is
    port (
        clk : in std_logic;
        reset: in std_logic
    );
    end component;
    signal clk : std_logic := '0';
    signal reset : std_logic := '0';

    constant clk_period : time := 10 ns;
begin

clk_process : process
begin
    while true loop
        clk <= '0';
        wait for clk_period / 2;
        clk <= '1';
        wait for clk_period / 2;
    end loop;
end process;

mpu_inst: mpu
 port map(
    clk => clk,
    reset => reset
);

sim_proc : process
begin
    wait for clk_period;
    reset <= '0';
    wait for 1000 ns;
    assert false report "Simulation" severity failure;
end process;

end architecture testbench;

work/mpu_tb.vcd
$date
  Sun Apr  6 18:02:57 2025
$end
$version
  GHDL v0
$end
$timescale
  1 fs
$end
$scope module standard $end
$upscope $end
$scope module textio $end
$upscope $end
$scope module std_logic_1164 $end
$upscope $end
$scope module numeric_std $end
$upscope $end
$scope module mpu_tb $end
$var reg 1 ! clk $end
$var reg 1 " reset $end
$scope module mpu_inst $end
$var reg 1 # clk $end
$var reg 1 $ reset $end
$var reg 1 % sela $end
$var reg 1 & selb $end
$var reg 1 ' rnw $end
$var reg 1 ( pc_ld $end
$var reg 1 ) ir_ld $end
$var reg 1 * acc_ld $end
$var reg 1 + acc_oe $end
$var reg 1 , accz $end
$var reg 1 - acc15 $end
$var reg 4 . opcode[3:0] $end
$var reg 4 / alufs[3:0] $end
$var reg 16 0 alu_in1[15:0] $end
$var reg 16 1 alu_in2[15:0] $end
$var reg 16 2 alu_out[15:0] $end
$var reg 1 3 oe_enable_signal $end
$var reg 12 4 ir_out[11:0] $end
$var reg 12 5 pc_out[11:0] $end
$var reg 16 6 membus[15:0] $end
$var reg 12 7 addressbus[11:0] $end
$scope module sequencer_inst $end
$var reg 1 8 clk $end
$var reg 1 9 reset $end
$var reg 4 : opcode[3:0] $end
$var reg 1 ; accz $end
$var reg 1 < acc15 $end
$var reg 1 = sela $end
$var reg 1 > selb $end
$var reg 1 ? rnw $end
$var reg 1 @ pc_ld $end
$var reg 1 A ir_ld $end
$var reg 1 B acc_ld $end
$var reg 1 C acc_oe $end
$var reg 4 D alufs[3:0] $end
$var reg 4 E q[3:0] $end
$var reg 4 F q_next[3:0] $end
$upscope $end
$scope module mem_block_inst $end
$var reg 1 G clk $end
$var reg 1 H reset $end
$var reg 1 I rnw $end
$var reg 12 J addr[11:0] $end
$var reg 16 K data_in[15:0] $end
$var reg 16 L data_out[15:0] $end
$comment memory is not handled $end
$upscope $end
$scope module memvalmux_inst $end
$var reg 16 M a[15:0] $end
$var reg 12 N b[11:0] $end
$var reg 1 O sel $end
$var reg 16 P s[15:0] $end
$upscope $end
$scope module acc_inst $end
$var reg 16 Q data_in[15:0] $end
$var reg 1 R acc_ld $end
$var reg 1 S clk $end
$var reg 16 T data_out[15:0] $end
$var reg 1 U accz $end
$var reg 1 V acc15 $end
$var reg 16 W accumulator[15:0] $end
$upscope $end
$scope module alu_inst $end
$var reg 16 X a[15:0] $end
$var reg 16 Y b[15:0] $end
$var reg 4 Z alufs[3:0] $end
$var reg 16 [ s[15:0] $end
$upscope $end
$scope module oe_inst $end
$var reg 16 \ data_in[15:0] $end
$var reg 1 ] en $end
$var reg 16 ^ data_out[15:0] $end
$upscope $end
$scope module ir_inst $end
$var reg 16 _ data_in[15:0] $end
$var reg 1 ` ir_ld $end
$var reg 12 a data_out[11:0] $end
$var reg 4 b opcode[3:0] $end
$var reg 16 c data[15:0] $end
$upscope $end
$scope module pc_inst $end
$var reg 16 d data_in[15:0] $end
$var reg 1 e pc_ld $end
$var reg 1 f clk $end
$var reg 12 g data_out[11:0] $end
$var reg 16 h data[15:0] $end
$upscope $end
$scope module pcirmux_inst $end
$var reg 12 i a[11:0] $end
$var reg 12 j b[11:0] $end
$var reg 1 k sel $end
$var reg 12 l s[11:0] $end
$upscope $end
$upscope $end
$upscope $end
$enddefinitions $end
#0
0!
0"
0#
0$
U%
U&
U'
U(
U)
U*
U+
0,
0-
b0000 .
b00UU /
bUUUUUUUUUUUUUUUU 0
bUUUU000000000000 1
b0000000000000000 2
U3
b000000000000 4
b000000000000 5
bUUUUUUUUUUUUUUUU 6
b000000000000 7
08
09
b0000 :
0;
0<
U=
U>
U?
U@
UA
UB
UC
b00UU D
bUUUU E
bUUUU F
0G
0H
UI
b000000000000 J
bUUUUUUUUUUUUUUUU K
bUUUUUUUUUUUUUUUU L
bUUUUUUUUUUUUUUUU M
b000000000000 N
UO
bUUUU000000000000 P
b0000000000000000 Q
UR
0S
bUUUUUUUUUUUUUUUU T
0U
0V
bUUUUUUUUUUUUUUUU W
bUUUUUUUUUUUUUUUU X
bUUUU000000000000 Y
b00UU Z
b0000000000000000 [
bUUUUUUUUUUUUUUUU \
U]
bUUUUUUUUUUUUUUUU ^
bUUUUUUUUUUUUUUUU _
U`
b000000000000 a
b0000 b
b0000000000000000 c
b0000000000000000 d
Ue
0f
b000000000000 g
b0000000000000000 h
b000000000000 i
b000000000000 j
Uk
b000000000000 l
#5000000
1!
1#
18
1G
bUUUUUUUUUUUUUUUU L
1S
bUUUUUUUUUUUUUUUU ^
1f
#10000000
0!
0#
08
0G
0S
0f
#15000000
1!
1#
18
1G
bUUUUUUUUUUUUUUUU L
1S
bUUUUUUUUUUUUUUUU ^
1f
#20000000
0!
0#
08
0G
0S
0f
#25000000
1!
1#
18
1G
bUUUUUUUUUUUUUUUU L
1S
bUUUUUUUUUUUUUUUU ^
1f
#30000000
0!
0#
08
0G
0S
0f
#35000000
1!
1#
18
1G
bUUUUUUUUUUUUUUUU L
1S
bUUUUUUUUUUUUUUUU ^
1f
#40000000
0!
0#
08
0G
0S
0f
#45000000
1!
1#
18
1G
bUUUUUUUUUUUUUUUU L
1S
bUUUUUUUUUUUUUUUU ^
1f
#50000000
0!
0#
08
0G
0S
0f
#55000000
1!
1#
18
1G
bUUUUUUUUUUUUUUUU L
1S
bUUUUUUUUUUUUUUUU ^
1f
#60000000
0!
0#
08
0G
0S
0f
#65000000
1!
1#
18
1G
bUUUUUUUUUUUUUUUU L
1S
bUUUUUUUUUUUUUUUU ^
1f
#70000000
0!
0#
08
0G
0S
0f
#75000000
1!
1#
18
1G
bUUUUUUUUUUUUUUUU L
1S
bUUUUUUUUUUUUUUUU ^
1f
#80000000
0!
0#
08
0G
0S
0f
#85000000
1!
1#
18
1G
bUUUUUUUUUUUUUUUU L
1S
bUUUUUUUUUUUUUUUU ^
1f
#90000000
0!
0#
08
0G
0S
0f
#95000000
1!
1#
18
1G
bUUUUUUUUUUUUUUUU L
1S
bUUUUUUUUUUUUUUUU ^
1f
#100000000
0!
0#
08
0G
0S
0f
#105000000
1!
1#
18
1G
bUUUUUUUUUUUUUUUU L
1S
bUUUUUUUUUUUUUUUU ^
1f
#110000000
0!
0#
08
0G
0S
0f
#115000000
1!
1#
18
1G
bUUUUUUUUUUUUUUUU L
1S
bUUUUUUUUUUUUUUUU ^
1f
#120000000
0!
0#
08
0G
0S
0f
#125000000
1!
1#
18
1G
bUUUUUUUUUUUUUUUU L
1S
bUUUUUUUUUUUUUUUU ^
1f
#130000000
0!
0#
08
0G
0S
0f
#135000000
1!
1#
18
1G
bUUUUUUUUUUUUUUUU L
1S
bUUUUUUUUUUUUUUUU ^
1f
#140000000
0!
0#
08
0G
0S
0f
#145000000
1!
1#
18
1G
bUUUUUUUUUUUUUUUU L
1S
bUUUUUUUUUUUUUUUU ^
1f
#150000000
0!
0#
08
0G
0S
0f
#155000000
1!
1#
18
1G
bUUUUUUUUUUUUUUUU L
1S
bUUUUUUUUUUUUUUUU ^
1f
#160000000
0!
0#
08
0G
0S
0f
#165000000
1!
1#
18
1G
bUUUUUUUUUUUUUUUU L
1S
bUUUUUUUUUUUUUUUU ^
1f
#170000000
0!
0#
08
0G
0S
0f
#175000000
1!
1#
18
1G
bUUUUUUUUUUUUUUUU L
1S
bUUUUUUUUUUUUUUUU ^
1f
#180000000
0!
0#
08
0G
0S
0f
#185000000
1!
1#
18
1G
bUUUUUUUUUUUUUUUU L
1S
bUUUUUUUUUUUUUUUU ^
1f
#190000000
0!
0#
08
0G
0S
0f
#195000000
1!
1#
18
1G
bUUUUUUUUUUUUUUUU L
1S
bUUUUUUUUUUUUUUUU ^
1f
#200000000
0!
0#
08
0G
0S
0f
#205000000
1!
1#
18
1G
bUUUUUUUUUUUUUUUU L
1S
bUUUUUUUUUUUUUUUU ^
1f
#210000000
0!
0#
08
0G
0S
0f
#215000000
1!
1#
18
1G
bUUUUUUUUUUUUUUUU L
1S
bUUUUUUUUUUUUUUUU ^
1f
#220000000
0!
0#
08
0G
0S
0f
#225000000
1!
1#
18
1G
bUUUUUUUUUUUUUUUU L
1S
bUUUUUUUUUUUUUUUU ^
1f
#230000000
0!
0#
08
0G
0S
0f
#235000000
1!
1#
18
1G
bUUUUUUUUUUUUUUUU L
1S
bUUUUUUUUUUUUUUUU ^
1f
#240000000
0!
0#
08
0G
0S
0f
#245000000
1!
1#
18
1G
bUUUUUUUUUUUUUUUU L
1S
bUUUUUUUUUUUUUUUU ^
1f
#250000000
0!
0#
08
0G
0S
0f
#255000000
1!
1#
18
1G
bUUUUUUUUUUUUUUUU L
1S
bUUUUUUUUUUUUUUUU ^
1f
#260000000
0!
0#
08
0G
0S
0f
#265000000
1!
1#
18
1G
bUUUUUUUUUUUUUUUU L
1S
bUUUUUUUUUUUUUUUU ^
1f
#270000000
0!
0#
08
0G
0S
0f
#275000000
1!
1#
18
1G
bUUUUUUUUUUUUUUUU L
1S
bUUUUUUUUUUUUUUUU ^
1f
#280000000
0!
0#
08
0G
0S
0f
#285000000
1!
1#
18
1G
bUUUUUUUUUUUUUUUU L
1S
bUUUUUUUUUUUUUUUU ^
1f
#290000000
0!
0#
08
0G
0S
0f
#295000000
1!
1#
18
1G
bUUUUUUUUUUUUUUUU L
1S
bUUUUUUUUUUUUUUUU ^
1f
#300000000
0!
0#
08
0G
0S
0f
#305000000
1!
1#
18
1G
bUUUUUUUUUUUUUUUU L
1S
bUUUUUUUUUUUUUUUU ^
1f
#310000000
0!
0#
08
0G
0S
0f
#315000000
1!
1#
18
1G
bUUUUUUUUUUUUUUUU L
1S
bUUUUUUUUUUUUUUUU ^
1f
#320000000
0!
0#
08
0G
0S
0f
#325000000
1!
1#
18
1G
bUUUUUUUUUUUUUUUU L
1S
bUUUUUUUUUUUUUUUU ^
1f
#330000000
0!
0#
08
0G
0S
0f
#335000000
1!
1#
18
1G
bUUUUUUUUUUUUUUUU L
1S
bUUUUUUUUUUUUUUUU ^
1f
#340000000
0!
0#
08
0G
0S
0f
#345000000
1!
1#
18
1G
bUUUUUUUUUUUUUUUU L
1S
bUUUUUUUUUUUUUUUU ^
1f
#350000000
0!
0#
08
0G
0S
0f
#355000000
1!
1#
18
1G
bUUUUUUUUUUUUUUUU L
1S
bUUUUUUUUUUUUUUUU ^
1f
#360000000
0!
0#
08
0G
0S
0f
#365000000
1!
1#
18
1G
bUUUUUUUUUUUUUUUU L
1S
bUUUUUUUUUUUUUUUU ^
1f
#370000000
0!
0#
08
0G
0S
0f
#375000000
1!
1#
18
1G
bUUUUUUUUUUUUUUUU L
1S
bUUUUUUUUUUUUUUUU ^
1f
#380000000
0!
0#
08
0G
0S
0f
#385000000
1!
1#
18
1G
bUUUUUUUUUUUUUUUU L
1S
bUUUUUUUUUUUUUUUU ^
1f
#390000000
0!
0#
08
0G
0S
0f
#395000000
1!
1#
18
1G
bUUUUUUUUUUUUUUUU L
1S
bUUUUUUUUUUUUUUUU ^
1f
#400000000
0!
0#
08
0G
0S
0f
#405000000
1!
1#
18
1G
bUUUUUUUUUUUUUUUU L
1S
bUUUUUUUUUUUUUUUU ^
1f
#410000000
0!
0#
08
0G
0S
0f
#415000000
1!
1#
18
1G
bUUUUUUUUUUUUUUUU L
1S
bUUUUUUUUUUUUUUUU ^
1f
#420000000
0!
0#
08
0G
0S
0f
#425000000
1!
1#
18
1G
bUUUUUUUUUUUUUUUU L
1S
bUUUUUUUUUUUUUUUU ^
1f
#430000000
0!
0#
08
0G
0S
0f
#435000000
1!
1#
18
1G
bUUUUUUUUUUUUUUUU L
1S
bUUUUUUUUUUUUUUUU ^
1f
#440000000
0!
0#
08
0G
0S
0f
#445000000
1!
1#
18
1G
bUUUUUUUUUUUUUUUU L
1S
bUUUUUUUUUUUUUUUU ^
1f
#450000000
0!
0#
08
0G
0S
0f
#455000000
1!
1#
18
1G
bUUUUUUUUUUUUUUUU L
1S
bUUUUUUUUUUUUUUUU ^
1f
#460000000
0!
0#
08
0G
0S
0f
#465000000
1!
1#
18
1G
bUUUUUUUUUUUUUUUU L
1S
bUUUUUUUUUUUUUUUU ^
1f
#470000000
0!
0#
08
0G
0S
0f
#475000000
1!
1#
18
1G
bUUUUUUUUUUUUUUUU L
1S
bUUUUUUUUUUUUUUUU ^
1f
#480000000
0!
0#
08
0G
0S
0f
#485000000
1!
1#
18
1G
bUUUUUUUUUUUUUUUU L
1S
bUUUUUUUUUUUUUUUU ^
1f
#490000000
0!
0#
08
0G
0S
0f
#495000000
1!
1#
18
1G
bUUUUUUUUUUUUUUUU L
1S
bUUUUUUUUUUUUUUUU ^
1f
