src/pcIrMux.vhd
library IEEE;
use IEEE.std_logic_1164.all;

entity pcIrMux is
    Port (
        A : in STD_LOGIC_VECTOR(11 downto 0); -- pc
        B : in STD_LOGIC_VECTOR(11 downto 0); -- ir
        sel : in STD_LOGIC;
        s : out STD_LOGIC_VECTOR(11 downto 0)
    );
end pcIrMux;

architecture behavioralMux of pcIrMux is

begin
    process(A, B, sel)
    begin
        if sel = '0' then
            s <= A;
        else
            s <= B;
        end if;
    end process;

end architecture behavioralMux;

src/pc.vhd
library IEEE;

use IEEE.STD_LOGIC_1164.ALL;

use IEEE.NUMERIC_STD.ALL;



entity pc is
    Port (
        data_in   : in  STD_LOGIC_VECTOR(15 downto 0);
        pc_ld        : in  STD_LOGIC;
        clk : in std_logic;
        reset : in std_logic;
        data_out  : out STD_LOGIC_VECTOR(11 downto 0)
    );
end pc;



architecture Behavioral_PC of pc is
    signal counter : unsigned(11 downto 0) := (others => '0');

begin

process(clk)
begin
    if reset = '1' then
        counter <= (others => '0');
    elsif rising_edge(clk) then
        if pc_ld = '1' then
            counter <= unsigned(data_in(11 downto 0));
        else
            counter <= counter + 1;
        end if;
    end if;
end process;

       data_out <= std_logic_vector(counter);

end Behavioral_PC;

src/ir.vhd
library IEEE;

use IEEE.STD_LOGIC_1164.ALL;

use IEEE.NUMERIC_STD.ALL;



entity ir is
    Port (
        data_in   : in  STD_LOGIC_VECTOR(15 downto 0);
        clk : in std_logic;
        ir_ld        : in  STD_LOGIC;
        data_out  : out STD_LOGIC_VECTOR(11 downto 0);
        opcode  : out STD_LOGIC_VECTOR(3 downto 0)
    );
end ir;



architecture Behavioral_IR of ir is

    signal data : STD_LOGIC_VECTOR(15 downto 0) := (others => '0');

begin

process(clk, ir_ld, data_in)

    begin
        if rising_edge(clk) then
            if ir_ld = '1' then
                data <= data_in;
            end if;
        end if;
    end process;

       opcode <= data(15 downto 12);

       data_out <= data(11 downto 0);

end Behavioral_IR;

src/oe.vhd
library IEEE;
use IEEE.std_logic_1164.all;

entity oe is
    port (
        data_in : in std_logic_vector(15 downto 0);
        en : in std_logic;
        data_out : out std_logic_vector(15 downto 0)
    );
end entity oe;

architecture rtl of oe is

begin

    process(data_in, en)
    begin
        if en = '1' then
            data_out <= data_in;
        else
            data_out <= (others => 'Z');
        end if;
    end process;


end architecture rtl;

src/alu.vhd
library IEEE;

use IEEE.STD_LOGIC_1164.ALL;

use IEEE.NUMERIC_STD.ALL;

entity alu is
    port (
        A : in std_logic_vector(15 downto 0);
        B : in std_logic_vector(15 downto 0);
        alufs : in std_logic_vector(3 downto 0);
        S : out std_logic_vector(15 downto 0)
    );
end entity alu;

architecture rtl of alu is

begin

    process (A, B, alufs)
    begin
        case alufs is
            when X"0" => S <= B;
            when X"1" => S <= std_logic_vector(unsigned(B) + 1);
            when X"2" => S <= std_logic_vector(unsigned(A) + unsigned(B));
            when X"3" => S <= std_logic_vector(unsigned(A) - unsigned(B));
            when others => S <= ( others => '0' );
        end case;
    end process;
end architecture rtl;

src/acc.vhd
library IEEE;

use IEEE.STD_LOGIC_1164.ALL;

use IEEE.NUMERIC_STD.ALL;

entity acc is
    port (
        data_in : in std_logic_vector(15 downto 0);
        acc_ld : in std_logic;
        clk : in std_logic;
        data_out : out std_logic_vector(15 downto 0);
        accZ : out std_logic;
        acc15 : out std_logic
    );
end entity acc;

architecture accB of acc is
    signal accumulator : std_logic_vector(15 downto 0);

begin
    process(clk, acc_ld, data_in)
    begin
        if rising_edge(clk) then
            if acc_ld = '1' then
                accumulator <= data_in;
            end if;
        end if;
    end process;

    data_out <= accumulator;
    accZ <= '1' when accumulator = X"0000" else '0';
    acc15 <= '1' when accumulator >= X"0000" else '0';

end architecture accB;

src/2bitmux.vhd
library IEEE;

use IEEE.STD_LOGIC_1164.ALL;

use IEEE.NUMERIC_STD.ALL;

entity memValMux is
    Port (
        A : in STD_LOGIC_VECTOR(15 downto 0); -- bus de donnees
        B : in STD_LOGIC_VECTOR(11 downto 0); -- bus d'addresse
        sel : in STD_LOGIC;
        s : out STD_LOGIC_VECTOR(15 downto 0)
    );
end memValMux;

architecture behavioralMux of memValMux is

begin
    process(A, B, sel)
    begin
        if sel = '0' then
            s <= A;
        else
            s(11 downto 0) <= B;
        end if;
    end process;

end architecture behavioralMux;

src/memory_block.vhd
library IEEE;

use IEEE.STD_LOGIC_1164.ALL;

use IEEE.NUMERIC_STD.ALL;



entity mem_block is
    Port (
        clk     : in  STD_LOGIC;                      -- Horloge
        reset   : in  STD_LOGIC;                      -- Réinitialisation
        RnW     : in  STD_LOGIC;                      -- Lecture/Écriture
        addr    : in  STD_LOGIC_VECTOR(11 downto 0);  -- Bus d'adresses (12 bits)
        data : inout  STD_LOGIC_VECTOR(15 downto 0)  -- Données d'entrée (16 bits)
    );
end mem_block;



architecture Behavioral_mem of mem_block is

    -- Déclaration de la mémoire : 4096 mots (2^12 adresses), 16 bits chacun

    type memory_array is array (0 to 4095) of STD_LOGIC_VECTOR(15 downto 0);

    signal memory : memory_array;

begin

    process(clk, reset)

    begin

        if reset = '1' then
         memory <= (
	    	      0    => X"2100",  -- LDA @100h (opcode 21, adresse 0100h)

	    	      1    => X"3101",  -- ADD @101h (opcode 31, adresse 0101h)

	    	      2    => X"5404",  -- JNE  @004h (opcode 54, adresse 0004h)

	    	      3    => X"4100",  -- SUB @100h (opcode 41, adresse 0100h)

	    	      4    => X"4100",  -- SUB @100h

	    	      5    => X"3100",  -- ADD @100h

	    	      6    => X"0000",  -- STP  (Stop)




	    	      256  => X"ABCD",  -- Donnée aléatoire à l'adresse 100h

	    	      257  => X"1234",  -- Donnée aléatoire à l'adresse 101h

	    	      258  => X"5678",  -- Donnée aléatoire

	    	      259  => X"9ABC",  -- Donnée aléatoire

	    	      260  => X"DEFA",  -- Donnée aléatoire

	    	      261  => X"1357",  -- Donnée aléatoire

	    	      262  => X"2468",  -- Donnée aléatoire

	    	      263  => X"FACE",  -- Donnée aléatoire

	    	      264  => X"BEAD",  -- Donnée aléatoire

	    	      265  => X"C0DE",  -- Donnée aléatoire

	    	      others => (others => '0') -- Initialisation des autres adresses à 0
	    	      );
            data <= (others => '0');

        elsif rising_edge(clk) then

            if RnW = '0' then  -- Mode écriture
                memory(to_integer(unsigned(addr))) <= data;
            else  -- Mode lecture
                data <= memory(to_integer(unsigned(addr)));
            end if;

        end if;

    end process;

end Behavioral_mem;

src/sequencer.vhd
library IEEE;

use IEEE.STD_LOGIC_1164.ALL;



entity sequencer is

    Port (
        clk    : in  std_logic;
        reset  : in  std_logic;
        opcode : in  std_logic_vector(3 downto 0);
        accZ   : in  std_logic;
        acc15  : in  std_logic;
        selA   : out std_logic;
        selB   : out std_logic;
        RnW   : out std_logic;
        pc_ld  : out std_logic;
        ir_ld  : out std_logic;
        acc_ld : out std_logic;
        acc_oe : out std_logic;
        alufs : out std_logic_vector(3 downto 0)
    );

end sequencer;





architecture structural_seq of sequencer is
    type state_type is (fetch, decode, execute, halt);
    signal curr_state, next_state : state_type := fetch;
begin
    state_reg:process(clk, reset)
    begin
        if reset = '1' then
            curr_state <= fetch;
        elsif rising_edge(clk) then
            curr_state <= next_state;
        end if;
    end process;
    next_state_logic: process(curr_state, opcode, accZ, acc15)
    begin
        case curr_state is
            when fetch =>
                next_state <= decode;
            when decode =>
                if opcode = "0111" then
                    next_state <= halt;
                else
                    next_state <= execute;
                end if;
            when execute =>
                next_state <= fetch;
            when halt =>
                next_state <= halt;
        end case;
    end process;
    output_logic: process(curr_state, opcode, accZ, acc15)
    begin
        selA <= '0';
        selB <= '0';
        RnW <= '0';
        pc_ld <= '0';
        ir_ld <= '0';
        acc_ld <= '0';
        acc_oe <= '0';
        alufs <= "0000";
        case curr_state is
            when fetch =>
                RnW <= '1';
                selA <= '0';
                ir_ld <= '1';
            when decode =>

            when execute =>
                case opcode is
                    when "0000" =>
                        RnW <= '1';
                        selB <= '1';
                        selA <= '1';
                        acc_ld <= '1';
                        alufs <= "0000";
                    when "0001" =>
                        RnW <= '0';
                        selA <= '1';
                        acc_oe <= '1';
                        acc_ld <= '1';
                    when "0010" =>
                        selA <= '1';
                        selB <= '1';
                        acc_ld <= '1';
                        RnW <= '1';
                        alufs <= "0010";
                    when "0011" =>
                        selA <= '1';
                        selB <= '1';
                        acc_ld <= '1';
                        RnW <= '1';
                        alufs <= "0001";
                    when "0100" =>
                        RnW <= '1';
                        selB <= '0';
                        alufs <= "0000";
                        pc_ld <= '1';
                    when "0101" =>
                        if acc15 = '1' then
                            RnW <= '1';
                            selB <= '0';
                            alufs <= "0000";
                            pc_ld <= '1';
                        end if;
                    when "0110" =>
                        if accZ = '0' then
                            RnW <= '1';
                            selB <= '0';
                            alufs <= "0000";
                            pc_ld <= '1';
                        end if;
                    when "0111" =>
                        selA <= '0';
                        selB <= '0';
                        RnW <= '0';
                        pc_ld <= '0';
                        ir_ld <= '0';
                        acc_ld <= '0';
                        acc_oe <= '0';
                        alufs <= "0000";
                    when others =>
                end case;
            when halt =>
        end case;
    end process;
end structural_seq;

src/mpu.vhd
library IEEE;
use IEEE.STD_LOGIC_1164.ALL;

entity mpu is
    port (
        clk : in std_logic;
        reset: in std_logic
    );
end entity mpu;

architecture rtl of mpu is

    component sequencer is
    Port (
        clk    : in  std_logic;
        reset  : in  std_logic;
        opcode : in  std_logic_vector(3 downto 0);
        accZ   : in  std_logic;
        acc15  : in  std_logic;
        selA   : out std_logic;
        selB   : out std_logic;
        RnW   : out std_logic;
        pc_ld  : out std_logic;
        ir_ld  : out std_logic;
        acc_ld : out std_logic;
        acc_oe : out std_logic;
        alufs : out std_logic_vector(3 downto 0)
    );
    end component;
    component memValMux is
    Port (
        A : in STD_LOGIC_VECTOR(15 downto 0); -- bus de donnees
        B : in STD_LOGIC_VECTOR(11 downto 0); -- bus d'addresse
        sel : in STD_LOGIC;
        s : out STD_LOGIC_VECTOR(15 downto 0)
    );
    end component;
    component acc is
    port (
        data_in : in std_logic_vector(15 downto 0);
        acc_ld : in std_logic;
        clk : in std_logic;
        data_out : out std_logic_vector(15 downto 0);
        accZ : out std_logic;
        acc15 : out std_logic
    );
    end component;
    component alu is
    port (
        A : in std_logic_vector(15 downto 0);
        B : in std_logic_vector(15 downto 0);
        alufs : in std_logic_vector(3 downto 0);
        S : out std_logic_vector(15 downto 0)
    );
    end component;
    component ir is
    Port (
        data_in   : in  STD_LOGIC_VECTOR(15 downto 0);
        ir_ld        : in  STD_LOGIC;
        clk : in std_logic;
        data_out  : out STD_LOGIC_VECTOR(11 downto 0);
        opcode  : out STD_LOGIC_VECTOR(3 downto 0)
    );
    end component;
    component mem_block is
    Port (
        clk     : in  STD_LOGIC;                      -- Horloge
        reset   : in  STD_LOGIC;                      -- Réinitialisation
        RnW     : in  STD_LOGIC;                      -- Lecture/Écriture
        addr    : in  STD_LOGIC_VECTOR(11 downto 0);  -- Bus d'adresses (12 bits)
        data : inout  STD_LOGIC_VECTOR(15 downto 0)  -- Données d'entrée (16 bits)
    );
    end component;
    component oe is
    port (
        data_in : in std_logic_vector(15 downto 0);
        en : in std_logic;
        data_out : out std_logic_vector(15 downto 0)
    );
    end component;

    component pc is
    Port (
        data_in   : in  STD_LOGIC_VECTOR(15 downto 0);
        pc_ld        : in  STD_LOGIC;
        clk : in std_logic;
        reset : in std_logic;
        data_out  : out STD_LOGIC_VECTOR(11 downto 0)
    );
    end component;
    component pcIrMux is
    Port (
        A : in STD_LOGIC_VECTOR(11 downto 0); -- pc
        B : in STD_LOGIC_VECTOR(11 downto 0); -- ir
        sel : in STD_LOGIC;
        s : out STD_LOGIC_VECTOR(11 downto 0)
    );
    end component;

    signal selA, selB, RnW, pc_ld, ir_ld, acc_ld, acc_oe, accZ, acc15 : std_logic;
    signal opcode, alufs : std_logic_vector(3 downto 0);
    signal alu_in1, alu_in2, alu_out: std_logic_vector(15 downto 0);
    signal ir_out, pc_out : std_logic_vector(11 downto 0);
    signal memBus : std_logic_vector(15 downto 0);
    signal addressBus : std_logic_vector(11 downto 0);

begin
sequencer_inst: sequencer
 port map(
    clk => clk,
    reset => reset,
    opcode => opcode,
    accZ => accZ,
    acc15 => acc15,
    selA => selA,
    selB => selB,
    RnW => RnW,
    pc_ld => pc_ld,
    ir_ld => ir_ld,
    acc_ld => acc_ld,
    acc_oe => acc_oe,
    alufs => alufs
);

mem_block_inst: mem_block
 port map(
    clk => clk,
    reset => reset,
    RnW => RnW,
    addr => addressBus,
    data => memBus
);

memValMux_inst: memValMux
 port map(
    A => memBus,
    B => addressBus,
    sel => selB,
    s => alu_in2
);

acc_inst: acc
 port map(
    clk => clk,
    data_in => alu_out,
    acc_ld => acc_ld,
    data_out => alu_in1,
    accZ => accZ,
    acc15 => acc15
);

alu_inst: alu
 port map(
    A => alu_in1,
    B => alu_in2,
    alufs => alufs,
    S => alu_out
);

oe_inst: oe
 port map(
    data_in => alu_in1,
    en => acc_oe,
    data_out => memBus
);
ir_inst: ir
 port map(
    data_in => memBus,
    ir_ld => ir_ld,
    clk => clk,
    data_out => ir_out,
    opcode => opcode
);

pc_inst: pc
 port map(
    data_in => alu_out,
    clk => clk,
    reset => reset,
    pc_ld => pc_ld,
    data_out => pc_out
);

pcIrMux_inst: pcIrMux
 port map(
    A => pc_out,
    B => ir_out,
    sel => selA,
    s => addressBus
);

end architecture rtl;

testbench/mpu_tb.vhd
library IEEE;
use IEEE.std_logic_1164.all;
use IEEE.numeric_std.all;

entity mpu_tb is
end entity mpu_tb;

architecture testbench of mpu_tb is
    component mpu is
    port (
        clk : in std_logic;
        reset: in std_logic
    );
    end component;
    signal clk : std_logic := '0';
    signal reset : std_logic := '1';

    constant clk_period : time := 10 ns;
begin

clk_process : process
begin
    while true loop
        clk <= '0';
        wait for clk_period / 2;
        clk <= '1';
        wait for clk_period / 2;
    end loop;
end process;

mpu_inst: mpu
 port map(
    clk => clk,
    reset => reset
);

sim_proc : process
begin
    wait for 30 ns;
    reset <= '0';
    wait for 1000 ns;
    assert false report "Simulation" severity failure;
end process;

end architecture testbench;

work/mpu_tb.vcd
$date
  Sun Apr  6 23:21:13 2025
$end
$version
  GHDL v0
$end
$timescale
  1 fs
$end
$scope module standard $end
$upscope $end
$scope module textio $end
$upscope $end
$scope module std_logic_1164 $end
$upscope $end
$scope module numeric_std $end
$upscope $end
$scope module mpu_tb $end
$var reg 1 ! clk $end
$var reg 1 " reset $end
$scope module mpu_inst $end
$var reg 1 # clk $end
$var reg 1 $ reset $end
$var reg 1 % sela $end
$var reg 1 & selb $end
$var reg 1 ' rnw $end
$var reg 1 ( pc_ld $end
$var reg 1 ) ir_ld $end
$var reg 1 * acc_ld $end
$var reg 1 + acc_oe $end
$var reg 1 , accz $end
$var reg 1 - acc15 $end
$var reg 4 . opcode[3:0] $end
$var reg 4 / alufs[3:0] $end
$var reg 16 0 alu_in1[15:0] $end
$var reg 16 1 alu_in2[15:0] $end
$var reg 16 2 alu_out[15:0] $end
$var reg 12 3 ir_out[11:0] $end
$var reg 12 4 pc_out[11:0] $end
$var reg 16 5 membus[15:0] $end
$var reg 12 6 addressbus[11:0] $end
$scope module sequencer_inst $end
$var reg 1 7 clk $end
$var reg 1 8 reset $end
$var reg 4 9 opcode[3:0] $end
$var reg 1 : accz $end
$var reg 1 ; acc15 $end
$var reg 1 < sela $end
$var reg 1 = selb $end
$var reg 1 > rnw $end
$var reg 1 ? pc_ld $end
$var reg 1 @ ir_ld $end
$var reg 1 A acc_ld $end
$var reg 1 B acc_oe $end
$var reg 4 C alufs[3:0] $end
$comment curr_state is not handled $end
$comment next_state is not handled $end
$upscope $end
$scope module mem_block_inst $end
$var reg 1 D clk $end
$var reg 1 E reset $end
$var reg 1 F rnw $end
$var reg 12 G addr[11:0] $end
$var reg 16 H data[15:0] $end
$comment memory is not handled $end
$upscope $end
$scope module memvalmux_inst $end
$var reg 16 I a[15:0] $end
$var reg 12 J b[11:0] $end
$var reg 1 K sel $end
$var reg 16 L s[15:0] $end
$upscope $end
$scope module acc_inst $end
$var reg 16 M data_in[15:0] $end
$var reg 1 N acc_ld $end
$var reg 1 O clk $end
$var reg 16 P data_out[15:0] $end
$var reg 1 Q accz $end
$var reg 1 R acc15 $end
$var reg 16 S accumulator[15:0] $end
$upscope $end
$scope module alu_inst $end
$var reg 16 T a[15:0] $end
$var reg 16 U b[15:0] $end
$var reg 4 V alufs[3:0] $end
$var reg 16 W s[15:0] $end
$upscope $end
$scope module oe_inst $end
$var reg 16 X data_in[15:0] $end
$var reg 1 Y en $end
$var reg 16 Z data_out[15:0] $end
$upscope $end
$scope module ir_inst $end
$var reg 16 [ data_in[15:0] $end
$var reg 1 \ clk $end
$var reg 1 ] ir_ld $end
$var reg 12 ^ data_out[11:0] $end
$var reg 4 _ opcode[3:0] $end
$var reg 16 ` data[15:0] $end
$upscope $end
$scope module pc_inst $end
$var reg 16 a data_in[15:0] $end
$var reg 1 b pc_ld $end
$var reg 1 c clk $end
$var reg 1 d reset $end
$var reg 12 e data_out[11:0] $end
$var reg 12 f counter[11:0] $end
$upscope $end
$scope module pcirmux_inst $end
$var reg 12 g a[11:0] $end
$var reg 12 h b[11:0] $end
$var reg 1 i sel $end
$var reg 12 j s[11:0] $end
$upscope $end
$upscope $end
$upscope $end
$enddefinitions $end
#0
0!
1"
0#
1$
0%
0&
1'
0(
1)
0*
0+
0,
0-
b0000 .
b0000 /
bUUUUUUUUUUUUUUUU 0
b0000000000000000 1
b0000000000000000 2
b000000000000 3
b000000000000 4
b0000000000000000 5
b000000000000 6
07
18
b0000 9
0:
0;
0<
0=
1>
0?
1@
0A
0B
b0000 C
0D
1E
1F
b000000000000 G
b0000000000000000 H
b0000000000000000 I
b000000000000 J
0K
b0000000000000000 L
b0000000000000000 M
0N
0O
bUUUUUUUUUUUUUUUU P
0Q
0R
bUUUUUUUUUUUUUUUU S
bUUUUUUUUUUUUUUUU T
b0000000000000000 U
b0000 V
b0000000000000000 W
bUUUUUUUUUUUUUUUU X
0Y
b0000000000000000 Z
b0000000000000000 [
0\
1]
b000000000000 ^
b0000 _
b0000000000000000 `
b0000000000000000 a
0b
0c
1d
b000000000000 e
b000000000000 f
b000000000000 g
b000000000000 h
0i
b000000000000 j
#5000000
1!
1#
17
1D
1O
b0000000000000000 Z
1\
1c
#10000000
0!
0#
07
0D
0O
b0000000000000000 Z
0\
0c
#15000000
1!
1#
17
1D
1O
b0000000000000000 Z
1\
1c
#20000000
0!
0#
07
0D
0O
b0000000000000000 Z
0\
0c
#25000000
1!
1#
17
1D
1O
b0000000000000000 Z
1\
1c
#30000000
0!
0"
0#
0$
07
08
0D
0E
0O
0\
0c
0d
#35000000
1!
1#
0'
0)
b0010000100000000 1
b0010000100000000 2
b000000000001 4
b0010000100000000 5
b000000000001 6
17
0>
0@
1D
0F
b000000000001 G
b0010000100000000 H
b0010000100000000 I
b000000000001 J
b0010000100000000 L
b0010000100000000 M
1O
b0010000100000000 U
b0010000100000000 W
b0010000100000000 Z
b0010000100000000 [
1\
0]
b0010000100000000 a
1c
b000000000001 e
b000000000001 f
b000000000001 g
b000000000001 j
#40000000
0!
0#
07
0D
0O
0\
0c
#45000000
1!
1#
1%
1&
1'
1*
b0010000000000000 1
b0010000000000000 2
b000000000010 4
b000000000000 6
17
1<
1=
1>
1A
1D
1F
b000000000000 G
b000000000000 J
1K
b0010000000000000 L
b0010000000000000 M
1N
1O
b0010000000000000 U
b0010000000000000 W
1\
b0010000000000000 a
1c
b000000000010 e
b000000000010 f
b000000000010 g
1i
b000000000000 j
#50000000
0!
0#
07
0D
0O
0\
0c
#55000000
1!
1#
0%
0&
1)
0*
1-
b0010000000000000 0
b0010000100000000 1
b0010000100000000 2
b000000000011 4
b000000000011 6
17
1;
0<
0=
1>
1@
0A
1D
b000000000011 G
b000000000011 J
0K
b0010000100000000 L
b0010000100000000 M
0N
1O
b0010000000000000 P
1R
b0010000000000000 S
b0010000000000000 T
b0010000100000000 U
b0010000100000000 W
b0010000000000000 X
b0010000100000000 Z
1\
1]
b0010000100000000 a
1c
b000000000011 e
b000000000011 f
b000000000011 g
0i
b000000000011 j
#60000000
0!
0#
07
0D
0O
0\
0c
#65000000
1!
1#
0'
0)
b0010 .
b0100000100000000 1
b0100000100000000 2
b000100000000 3
b000000000100 4
b0100000100000000 5
b000000000100 6
17
b0010 9
0>
0@
1D
0F
b000000000100 G
b0100000100000000 H
b0100000100000000 I
b000000000100 J
b0100000100000000 L
b0100000100000000 M
1O
b0100000100000000 U
b0100000100000000 W
b0100000100000000 Z
b0100000100000000 [
1\
0]
b000100000000 ^
b0010 _
b0010000100000000 `
b0100000100000000 a
1c
b000000000100 e
b000000000100 f
b000000000100 g
b000100000000 h
b000000000100 j
#70000000
0!
0#
07
0D
0O
0\
0c
#75000000
1!
1#
1%
1&
1'
1*
b0010 /
b0100000100000000 1
b0110000100000000 2
b000000000101 4
b000100000000 6
17
1<
1=
1>
1A
b0010 C
1D
1F
b000100000000 G
b000100000000 J
1K
b0100000100000000 L
b0110000100000000 M
1N
1O
b0100000100000000 U
b0010 V
b0110000100000000 W
1\
b0110000100000000 a
1c
b000000000101 e
b000000000101 f
b000000000101 g
1i
b000100000000 j
#80000000
0!
0#
07
0D
0O
0\
0c
#85000000
1!
1#
0%
0&
1)
0*
b0000 /
b0110000100000000 0
b1010101111001101 1
b1010101111001101 2
b000000000110 4
b1010101111001101 5
b000000000110 6
17
0<
0=
1>
1@
0A
b0000 C
1D
b000000000110 G
b1010101111001101 H
b1010101111001101 I
b000000000110 J
0K
b1010101111001101 L
b1010101111001101 M
0N
1O
b0110000100000000 P
b0110000100000000 S
b0110000100000000 T
b1010101111001101 U
b0000 V
b1010101111001101 W
b0110000100000000 X
b1010101111001101 Z
b1010101111001101 [
1\
1]
b1010101111001101 a
1c
b000000000110 e
b000000000110 f
b000000000110 g
0i
b000000000110 j
#90000000
0!
0#
07
0D
0O
0\
0c
#95000000
1!
1#
0'
0)
b1010 .
b0000000000000000 1
b0000000000000000 2
b101111001101 3
b000000000111 4
b0000000000000000 5
b000000000111 6
17
b1010 9
0>
0@
1D
0F
b000000000111 G
b0000000000000000 H
b0000000000000000 I
b000000000111 J
b0000000000000000 L
b0000000000000000 M
1O
b0000000000000000 U
b0000000000000000 W
b0000000000000000 Z
b0000000000000000 [
1\
0]
b101111001101 ^
b1010 _
b1010101111001101 `
b0000000000000000 a
1c
b000000000111 e
b000000000111 f
b000000000111 g
b101111001101 h
b000000000111 j
#100000000
0!
0#
07
0D
0O
0\
0c
#105000000
1!
1#
b000000001000 4
b000000001000 6
17
1D
b000000001000 G
b000000001000 J
1O
1\
1c
b000000001000 e
b000000001000 f
b000000001000 g
b000000001000 j
#110000000
0!
0#
07
0D
0O
0\
0c
#115000000
1!
1#
1'
1)
b000000001001 4
b000000001001 6
17
1>
1@
1D
1F
b000000001001 G
b000000001001 J
1O
1\
1]
1c
b000000001001 e
b000000001001 f
b000000001001 g
b000000001001 j
#120000000
0!
0#
07
0D
0O
0\
0c
#125000000
1!
1#
0'
0)
b0000 .
b000000000000 3
b000000001010 4
b000000001010 6
17
b0000 9
0>
0@
1D
0F
b000000001010 G
b000000001010 J
1O
b0000000000000000 Z
1\
0]
b000000000000 ^
b0000 _
b0000000000000000 `
1c
b000000001010 e
b000000001010 f
b000000001010 g
b000000000000 h
b000000001010 j
#130000000
0!
0#
07
0D
0O
0\
0c
#135000000
1!
1#
1%
1&
1'
1*
b0000000000000000 1
b0000000000000000 2
b000000001011 4
b000000000000 6
17
1<
1=
1>
1A
1D
1F
b000000000000 G
b000000000000 J
1K
b0000000000000000 L
b0000000000000000 M
1N
1O
b0000000000000000 U
b0000000000000000 W
1\
b0000000000000000 a
1c
b000000001011 e
b000000001011 f
b000000001011 g
1i
b000000000000 j
#140000000
0!
0#
07
0D
0O
0\
0c
#145000000
1!
1#
0%
0&
1)
0*
1,
b0000000000000000 0
b0010000100000000 1
b0010000100000000 2
b000000001100 4
b0010000100000000 5
b000000001100 6
17
1:
0<
0=
1>
1@
0A
1D
b000000001100 G
b0010000100000000 H
b0010000100000000 I
b000000001100 J
0K
b0010000100000000 L
b0010000100000000 M
0N
1O
b0000000000000000 P
1Q
b0000000000000000 S
b0000000000000000 T
b0010000100000000 U
b0010000100000000 W
b0000000000000000 X
b0010000100000000 Z
b0010000100000000 [
1\
1]
b0010000100000000 a
1c
b000000001100 e
b000000001100 f
b000000001100 g
0i
b000000001100 j
#150000000
0!
0#
07
0D
0O
0\
0c
#155000000
1!
1#
0'
0)
b0010 .
b0000000000000000 1
b0000000000000000 2
b000100000000 3
b000000001101 4
b0000000000000000 5
b000000001101 6
17
b0010 9
0>
0@
1D
0F
b000000001101 G
b0000000000000000 H
b0000000000000000 I
b000000001101 J
b0000000000000000 L
b0000000000000000 M
1O
b0000000000000000 U
b0000000000000000 W
b0000000000000000 Z
b0000000000000000 [
1\
0]
b000100000000 ^
b0010 _
b0010000100000000 `
b0000000000000000 a
1c
b000000001101 e
b000000001101 f
b000000001101 g
b000100000000 h
b000000001101 j
#160000000
0!
0#
07
0D
0O
0\
0c
#165000000
1!
1#
1%
1&
1'
1*
b0010 /
b0000000100000000 1
b0000000100000000 2
b000000001110 4
b000100000000 6
17
1<
1=
1>
1A
b0010 C
1D
1F
b000100000000 G
b000100000000 J
1K
b0000000100000000 L
b0000000100000000 M
1N
1O
b0000000100000000 U
b0010 V
b0000000100000000 W
1\
b0000000100000000 a
1c
b000000001110 e
b000000001110 f
b000000001110 g
1i
b000100000000 j
#170000000
0!
0#
07
0D
0O
0\
0c
#175000000
1!
1#
0%
0&
1)
0*
0,
b0000 /
b0000000100000000 0
b1010101111001101 1
b1010101111001101 2
b000000001111 4
b1010101111001101 5
b000000001111 6
17
0:
0<
0=
1>
1@
0A
b0000 C
1D
b000000001111 G
b1010101111001101 H
b1010101111001101 I
b000000001111 J
0K
b1010101111001101 L
b1010101111001101 M
0N
1O
b0000000100000000 P
0Q
b0000000100000000 S
b0000000100000000 T
b1010101111001101 U
b0000 V
b1010101111001101 W
b0000000100000000 X
b1010101111001101 Z
b1010101111001101 [
1\
1]
b1010101111001101 a
1c
b000000001111 e
b000000001111 f
b000000001111 g
0i
b000000001111 j
#180000000
0!
0#
07
0D
0O
0\
0c
#185000000
1!
1#
0'
0)
b1010 .
b0000000000000000 1
b0000000000000000 2
b101111001101 3
b000000010000 4
b0000000000000000 5
b000000010000 6
17
b1010 9
0>
0@
1D
0F
b000000010000 G
b0000000000000000 H
b0000000000000000 I
b000000010000 J
b0000000000000000 L
b0000000000000000 M
1O
b0000000000000000 U
b0000000000000000 W
b0000000000000000 Z
b0000000000000000 [
1\
0]
b101111001101 ^
b1010 _
b1010101111001101 `
b0000000000000000 a
1c
b000000010000 e
b000000010000 f
b000000010000 g
b101111001101 h
b000000010000 j
#190000000
0!
0#
07
0D
0O
0\
0c
#195000000
1!
1#
b000000010001 4
b000000010001 6
17
1D
b000000010001 G
b000000010001 J
1O
1\
1c
b000000010001 e
b000000010001 f
b000000010001 g
b000000010001 j
#200000000
0!
0#
07
0D
0O
0\
0c
#205000000
1!
1#
1'
1)
b000000010010 4
b000000010010 6
17
1>
1@
1D
1F
b000000010010 G
b000000010010 J
1O
1\
1]
1c
b000000010010 e
b000000010010 f
b000000010010 g
b000000010010 j
#210000000
0!
0#
07
0D
0O
0\
0c
#215000000
1!
1#
0'
0)
b0000 .
b000000000000 3
b000000010011 4
b000000010011 6
17
b0000 9
0>
0@
1D
0F
b000000010011 G
b000000010011 J
1O
b0000000000000000 Z
1\
0]
b000000000000 ^
b0000 _
b0000000000000000 `
1c
b000000010011 e
b000000010011 f
b000000010011 g
b000000000000 h
b000000010011 j
#220000000
0!
0#
07
0D
0O
0\
0c
#225000000
1!
1#
1%
1&
1'
1*
b0000000000000000 1
b0000000000000000 2
b000000010100 4
b000000000000 6
17
1<
1=
1>
1A
1D
1F
b000000000000 G
b000000000000 J
1K
b0000000000000000 L
b0000000000000000 M
1N
1O
b0000000000000000 U
b0000000000000000 W
1\
b0000000000000000 a
1c
b000000010100 e
b000000010100 f
b000000010100 g
1i
b000000000000 j
#230000000
0!
0#
07
0D
0O
0\
0c
#235000000
1!
1#
0%
0&
1)
0*
1,
b0000000000000000 0
b0010000100000000 1
b0010000100000000 2
b000000010101 4
b0010000100000000 5
b000000010101 6
17
1:
0<
0=
1>
1@
0A
1D
b000000010101 G
b0010000100000000 H
b0010000100000000 I
b000000010101 J
0K
b0010000100000000 L
b0010000100000000 M
0N
1O
b0000000000000000 P
1Q
b0000000000000000 S
b0000000000000000 T
b0010000100000000 U
b0010000100000000 W
b0000000000000000 X
b0010000100000000 Z
b0010000100000000 [
1\
1]
b0010000100000000 a
1c
b000000010101 e
b000000010101 f
b000000010101 g
0i
b000000010101 j
#240000000
0!
0#
07
0D
0O
0\
0c
#245000000
1!
1#
0'
0)
b0010 .
b0000000000000000 1
b0000000000000000 2
b000100000000 3
b000000010110 4
b0000000000000000 5
b000000010110 6
17
b0010 9
0>
0@
1D
0F
b000000010110 G
b0000000000000000 H
b0000000000000000 I
b000000010110 J
b0000000000000000 L
b0000000000000000 M
1O
b0000000000000000 U
b0000000000000000 W
b0000000000000000 Z
b0000000000000000 [
1\
0]
b000100000000 ^
b0010 _
b0010000100000000 `
b0000000000000000 a
1c
b000000010110 e
b000000010110 f
b000000010110 g
b000100000000 h
b000000010110 j
#250000000
0!
0#
07
0D
0O
0\
0c
