src/pcIrMux.vhd
library IEEE;
use IEEE.std_logic_1164.all;

entity pcIrMux is
    Port (
        A : in STD_LOGIC_VECTOR(11 downto 0); -- pc
        B : in STD_LOGIC_VECTOR(11 downto 0); -- ir
        sel : in STD_LOGIC;
        s : out STD_LOGIC_VECTOR(11 downto 0)
    );
end pcIrMux;

architecture behavioralMux of pcIrMux is

begin
    process(A, B, sel)
    begin
        if sel = '0' then
            s <= A;
        else
            s <= B;
        end if;
    end process;

end architecture behavioralMux;

src/pc.vhd
library IEEE;

use IEEE.STD_LOGIC_1164.ALL;

use IEEE.NUMERIC_STD.ALL;



entity pc is
    Port (
        data_in   : in  STD_LOGIC_VECTOR(15 downto 0);
        clk : in std_logic;
        pc_ld        : in  STD_LOGIC;
        pc_inc : in std_logic;
        reset : in std_logic;
        data_out  : out STD_LOGIC_VECTOR(11 downto 0)
    );
end pc;



architecture Behavioral_PC of pc is
    signal counter : unsigned(11 downto 0) := (others => '0');

begin

process(reset, clk)
begin
    if rising_edge(clk) then
        if reset = '1' then
            counter <= (others => '0');
        elsif pc_ld = '1' then
                counter <= unsigned(data_in(11 downto 0));
        elsif pc_inc = '1' then
                counter <= counter + 1;
        end if;
    end if;
end process;

       data_out <= std_logic_vector(counter);

end Behavioral_PC;

src/ir.vhd
library IEEE;

use IEEE.STD_LOGIC_1164.ALL;

use IEEE.NUMERIC_STD.ALL;



entity ir is
    Port (
        data_in   : in  STD_LOGIC_VECTOR(15 downto 0);
        ir_ld        : in  STD_LOGIC;
        clk : in std_logic;
        data_out  : out STD_LOGIC_VECTOR(11 downto 0);
        opcode  : out STD_LOGIC_VECTOR(3 downto 0)
    );
end ir;



architecture Behavioral_IR of ir is

    signal data : STD_LOGIC_VECTOR(15 downto 0) := (others => '0');

begin

process(clk)

    begin
        if rising_edge(clk) then
            if ir_ld = '1' then
                data <= data_in;
            end if;
        end if;
    end process;

       opcode <= data(15 downto 12);

       data_out <= data(11 downto 0);

end Behavioral_IR;

src/oe.vhd
library IEEE;
use IEEE.std_logic_1164.all;

entity oe is
    port (
        data_in : in std_logic_vector(15 downto 0);
        clk : in std_logic;
        en : in std_logic;
        data_out : out std_logic_vector(15 downto 0)
    );
end entity oe;

architecture rtl of oe is

begin

    process(clk)
    begin
        if rising_edge(clk) then
            if en = '1' then
                data_out <= data_in;
            else
                data_out <= (others => 'Z');
            end if;
        end if;
    end process;


end architecture rtl;

src/alu.vhd
library IEEE;

use IEEE.STD_LOGIC_1164.ALL;

use IEEE.NUMERIC_STD.ALL;

entity alu is
    port (
        A : in std_logic_vector(15 downto 0);
        B : in std_logic_vector(15 downto 0);
        clk : in std_logic;
        alufs : in std_logic_vector(3 downto 0);
        S : out std_logic_vector(15 downto 0)
    );
end entity alu;

architecture rtl of alu is

begin
    S <= B when alufs = "0000" else
    std_logic_vector(unsigned(B) + 1) when alufs = "0001" else
    std_logic_vector(unsigned(A) + unsigned(B)) when alufs = "0010" else
    std_logic_vector(unsigned(A) - unsigned(B)) when alufs = "0011" else
    (others => '0');
end architecture rtl;

src/acc.vhd
library IEEE;

use IEEE.STD_LOGIC_1164.ALL;

use IEEE.NUMERIC_STD.ALL;

entity acc is
    port (
        data_in : in std_logic_vector(15 downto 0);
        acc_ld : in std_logic;
        clk : in std_logic;
        data_out : out std_logic_vector(15 downto 0);
        accZ : out std_logic;
        acc15 : out std_logic
    );
end entity acc;

architecture accB of acc is
    signal accumulator : std_logic_vector(15 downto 0);

begin
    process(clk, acc_ld, data_in)
    begin
        if rising_edge(clk) then
            if acc_ld = '1' then
                accumulator <= data_in;
            end if;
        end if;
    end process;

    data_out <= accumulator;
    accZ <= '1' when accumulator = X"0000" else '0';
    acc15 <= '1' when accumulator >= X"0000" else '0';

end architecture accB;

src/2bitmux.vhd
library IEEE;

use IEEE.STD_LOGIC_1164.ALL;

use IEEE.NUMERIC_STD.ALL;

entity memValMux is
    Port (
        A : in STD_LOGIC_VECTOR(15 downto 0); -- bus de donnees
        B : in STD_LOGIC_VECTOR(11 downto 0); -- bus d'addresse
        sel : in STD_LOGIC;
        s : out STD_LOGIC_VECTOR(15 downto 0)
    );
end memValMux;

architecture behavioralMux of memValMux is

begin
    process(A, B, sel)
    begin
        if sel = '0' then
            s <= A;
        else
            s(11 downto 0) <= B;
        end if;
    end process;

end architecture behavioralMux;

src/memory_block.vhd
library IEEE;

use IEEE.STD_LOGIC_1164.ALL;

use IEEE.NUMERIC_STD.ALL;



entity mem_block is
    Port (
        reset   : in  STD_LOGIC;                      -- Réinitialisation
        clk : in std_logic;
        RnW     : in  STD_LOGIC;                      -- Lecture/Écriture
        addr    : in  STD_LOGIC_VECTOR(11 downto 0);  -- Bus d'adresses (12 bits)
        data : inout  STD_LOGIC_VECTOR(15 downto 0)  -- Données d'entrée (16 bits)
    );
end mem_block;



architecture Behavioral_mem of mem_block is

    -- Déclaration de la mémoire : 4096 mots (2^12 adresses), 16 bits chacun

    type memory_array is array (0 to 4095) of STD_LOGIC_VECTOR(15 downto 0);

    signal memory : memory_array;
    signal data_in : std_logic_vector(15 downto 0);
    signal data_out : std_logic_vector(15 downto 0);

begin

    process(reset, clk)

    begin

        if reset = '1' then
         memory <= (
	    	      0    => X"0100",  -- LDA @100h (opcode 0, adresse 0100h)

	    	      1    => X"2101",  -- ADD @101h (opcode 0010, adresse 0101h)

	    	      2    => X"6005",  -- JNE  @004h (opcode 0110, adresse 0005h)

	    	      3    => X"3100",  -- SUB @100h (opcode 0011, adresse 0100h)

	    	      4    => X"3100",  -- SUB @100h

	    	      5    => X"2100",  -- ADD @100h

	    	      6    => X"7000",  -- STP  (Stop)


	    	      256  => X"1111",  -- Donnée aléatoire à l'adresse 100h

	    	      257  => X"2222",  -- Donnée aléatoire à l'adresse 101h

	    	      others => (others => '0') -- Initialisation des autres adresses à 0
	    	      );

        elsif rising_edge(clk) then
            if RnW = '0' then  -- Mode écriture
                memory(to_integer(unsigned(addr))) <= data_in;
            else  -- Mode lecture
                data_out <= memory(to_integer(unsigned(addr)));
            end if;
        end if;
    end process;
    data <= data_out when RnW = '1' else data_in;
end Behavioral_mem;

src/seqTwo.vhd
library IEEE;

use IEEE.STD_LOGIC_1164.ALL;



entity seqTwo is

    Port (
        clk    : in  std_logic;
        reset  : in  std_logic;
        opcode : in  std_logic_vector(3 downto 0);
        accZ   : in  std_logic;
        acc15  : in  std_logic;
        selA   : out std_logic;
        selB   : out std_logic;
        RnW   : out std_logic;
        pc_inc : out std_logic;
        pc_ld  : out std_logic;
        ir_ld  : out std_logic;
        acc_ld : out std_logic;
        acc_oe : out std_logic;
        alufs : out std_logic_vector(3 downto 0)
    );

end seqTwo;





architecture st_st of seqTwo is
    signal cs : std_logic_vector(1 downto 0) := "00"; -- fetch = 01, decode = 10, execute = 11, rst = halt = 00
    signal ns : std_logic_vector(1 downto 0) := "00";
begin
    state_reg:process(clk, reset)
    begin
        if rising_edge(clk) then
            cs <= ns;
        end if;
    end process;

    ns(0) <= (not cs(0) or cs(1)) and not reset and not (opcode(2) and opcode(1) and opcode(0));
    ns(1) <= ( (cs(0) and not cs(1)) or (cs(1) and not cs(0) ) ) and not reset and not (opcode(2) and opcode(1) and opcode(0));

    ir_ld <= cs(0) and not cs(1);
    Rnw <= '0' when (cs(1) = '1' and cs(0) = '0' and opcode = "0001") else '1';
    selA <= cs(1) and not cs(0) and not opcode(2) and not opcode(3);
    selB <= cs(1) and not cs(0) and not opcode(3) and not opcode(2) and not (opcode(0) and not opcode(1));
    acc_ld <= cs(1) and cs (0) and not opcode(3) and not opcode(2) and not ( opcode(0) and not opcode(1) );
    pc_ld <= cs(1) and not cs(0) and not opcode(3) and opcode(2) and ((opcode(1) and not opcode(0) and not accZ) or (opcode(0) and not opcode(1) and acc15));
    pc_inc <= cs(1) and not cs(0) and not opcode(3) and (not opcode(2) or (opcode(2) and ((opcode(1) and not opcode(0) and accZ) or (opcode(0) and not opcode(1) and not accZ))));
    acc_oe <= cs(1) and not cs(0) and not opcode(3) and not opcode(2) and not opcode (1) and opcode(0);
    alufs(3) <= '0';
    alufs(2) <= '0';
    alufs(1) <= cs(1) and cs(0) and not opcode(3) and not opcode(2) and opcode(1) and not opcode(0);
    alufs(0) <= cs(1) and cs(0) and not opcode(3) and not opcode(2) and opcode(1) and opcode(0);

end st_st;

src/mpu.vhd
library IEEE;
use IEEE.STD_LOGIC_1164.ALL;

entity mpu is
    port (
        clk : in std_logic;
        reset: in std_logic
    );
end entity mpu;

architecture rtl of mpu is

    component seqTwo is
    Port (
        clk    : in  std_logic;
        reset  : in  std_logic;
        opcode : in  std_logic_vector(3 downto 0);
        accZ   : in  std_logic;
        acc15  : in  std_logic;
        selA   : out std_logic;
        selB   : out std_logic;
        RnW   : out std_logic;
        pc_inc : out std_logic;
        pc_ld  : out std_logic;
        ir_ld  : out std_logic;
        acc_ld : out std_logic;
        acc_oe : out std_logic;
        alufs : out std_logic_vector(3 downto 0)
    );
    end component;
    component memValMux is
    Port (
        A : in STD_LOGIC_VECTOR(15 downto 0); -- bus de donnees
        B : in STD_LOGIC_VECTOR(11 downto 0); -- bus d'addresse
        sel : in STD_LOGIC;
        s : out STD_LOGIC_VECTOR(15 downto 0)
    );
    end component;
    component acc is
    port (
        data_in : in std_logic_vector(15 downto 0);
        acc_ld : in std_logic;
        clk : in std_logic;
        data_out : out std_logic_vector(15 downto 0);
        accZ : out std_logic;
        acc15 : out std_logic
    );
    end component;
    component alu is
    port (
        A : in std_logic_vector(15 downto 0);
        B : in std_logic_vector(15 downto 0);
        alufs : in std_logic_vector(3 downto 0);
        S : out std_logic_vector(15 downto 0)
    );
    end component;
    component ir is
    Port (
        data_in   : in  STD_LOGIC_VECTOR(15 downto 0);
        ir_ld        : in  STD_LOGIC;
        clk : in std_logic;
        data_out  : out STD_LOGIC_VECTOR(11 downto 0);
        opcode  : out STD_LOGIC_VECTOR(3 downto 0)
    );
    end component;
    component mem_block is
    Port (
        reset   : in  STD_LOGIC;                      -- Réinitialisation
        RnW     : in  STD_LOGIC;                      -- Lecture/Écriture
        clk : in std_logic;
        addr    : in  STD_LOGIC_VECTOR(11 downto 0);  -- Bus d'adresses (12 bits)
        data : inout std_logic_vector(15 downto 0)
    );
    end component;
    component oe is
    port (
        data_in : in std_logic_vector(15 downto 0);
        en : in std_logic;
        clk : in std_logic;
        data_out : out std_logic_vector(15 downto 0)
    );
    end component;

    component pc is
    Port (
        data_in   : in  STD_LOGIC_VECTOR(15 downto 0);
        pc_ld        : in  STD_LOGIC;
        pc_inc : in std_logic;
        clk : in std_logic;
        reset : in std_logic;
        data_out  : out STD_LOGIC_VECTOR(11 downto 0)
    );
    end component;
    component pcIrMux is
    Port (
        A : in STD_LOGIC_VECTOR(11 downto 0); -- pc
        B : in STD_LOGIC_VECTOR(11 downto 0); -- ir
        sel : in STD_LOGIC;
        s : out STD_LOGIC_VECTOR(11 downto 0)
    );
    end component;

    signal selA, selB, RnW, pc_ld,pc_inc, ir_ld, acc_ld, acc_oe, accZ, acc15 : std_logic;
    signal opcode, alufs : std_logic_vector(3 downto 0);
    signal alu_in1, alu_in2, alu_out: std_logic_vector(15 downto 0);
    signal ir_out, pc_out : std_logic_vector(11 downto 0);
    signal memBus : std_logic_vector(15 downto 0);
    signal addressBus : std_logic_vector(11 downto 0);

begin
sequencer_inst: seqTwo
 port map(
    clk => clk,
    reset => reset,
    opcode => opcode,
    accZ => accZ,
    acc15 => acc15,
    selA => selA,
    selB => selB,
    RnW => RnW,
    pc_inc => pc_inc,
    pc_ld => pc_ld,
    ir_ld => ir_ld,
    acc_ld => acc_ld,
    acc_oe => acc_oe,
    alufs => alufs
);


mem_block_inst: mem_block
 port map(
    reset => reset,
    RnW => RnW,
    clk => clk,
    addr => addressBus,
    data => memBus
);

memValMux_inst: memValMux
 port map(
    A => memBus,
    B => addressBus,
    sel => selB,
    s => alu_in2
);

acc_inst: acc
 port map(
    data_in => alu_out,
    acc_ld => acc_ld,
    data_out => alu_in1,
    clk => clk,
    accZ => accZ,
    acc15 => acc15
);

alu_inst: alu
 port map(
    A => alu_in1,
    B => alu_in2,
    alufs => alufs,
    S => alu_out
);

oe_inst: oe
 port map(
    data_in => alu_in1,
    en => acc_oe,
    clk => clk,
    data_out => memBus
);
ir_inst: ir
 port map(
    data_in => memBus,
    ir_ld => ir_ld,
    clk => clk,
    data_out => ir_out,
    opcode => opcode
);

pc_inst: pc
 port map(
    data_in => alu_out,
    reset => reset,
    clk => clk,
    pc_ld => pc_ld,
    pc_inc => pc_inc,
    data_out => pc_out
);

pcIrMux_inst: pcIrMux
 port map(
    A => pc_out,
    B => ir_out,
    sel => selA,
    s => addressBus
);

end architecture rtl;

testbench/mpu_tb.vhd
library IEEE;
use IEEE.std_logic_1164.all;
use IEEE.numeric_std.all;

entity mpu_tb is
end entity mpu_tb;

architecture testbench of mpu_tb is
    component mpu is
    port (
        clk : in std_logic;
        reset: in std_logic
    );
    end component;
    signal clk : std_logic := '0';
    signal reset : std_logic := '0';

    constant clk_period : time := 10 ns;
begin

clk_process : process
begin
    while true loop
        clk <= '0';
        wait for clk_period / 2;
        clk <= '1';
        wait for clk_period / 2;
    end loop;
end process;

mpu_inst: mpu
 port map(
    clk => clk,
    reset => reset
);

sim_proc : process
begin
    wait for clk_period;
    reset <= '0';
    wait for 1000 ns;
    assert false report "Simulation" severity failure;
end process;

end architecture testbench;

work/mpu_tb.vcd
$date
  Mon May 12 01:59:58 2025
$end
$version
  GHDL v0
$end
$timescale
  1 fs
$end
$scope module standard $end
$upscope $end
$scope module textio $end
$upscope $end
$scope module std_logic_1164 $end
$upscope $end
$scope module numeric_std $end
$upscope $end
$scope module mpu_tb $end
$var reg 1 ! clk $end
$var reg 1 " reset $end
$scope module mpu_inst $end
$var reg 1 # clk $end
$var reg 1 $ reset $end
$var reg 1 % sela $end
$var reg 1 & selb $end
$var reg 1 ' rnw $end
$var reg 1 ( pc_ld $end
$var reg 1 ) pc_inc $end
$var reg 1 * ir_ld $end
$var reg 1 + acc_ld $end
$var reg 1 , acc_oe $end
$var reg 1 - accz $end
$var reg 1 . acc15 $end
$var reg 4 / opcode[3:0] $end
$var reg 4 0 alufs[3:0] $end
$var reg 16 1 alu_in1[15:0] $end
$var reg 16 2 alu_in2[15:0] $end
$var reg 16 3 alu_out[15:0] $end
$var reg 12 4 ir_out[11:0] $end
$var reg 12 5 pc_out[11:0] $end
$var reg 16 6 membus[15:0] $end
$var reg 12 7 addressbus[11:0] $end
$scope module sequencer_inst $end
$var reg 1 8 clk $end
$var reg 1 9 reset $end
$var reg 4 : opcode[3:0] $end
$var reg 1 ; accz $end
$var reg 1 < acc15 $end
$var reg 1 = sela $end
$var reg 1 > selb $end
$var reg 1 ? rnw $end
$var reg 1 @ pc_inc $end
$var reg 1 A pc_ld $end
$var reg 1 B ir_ld $end
$var reg 1 C acc_ld $end
$var reg 1 D acc_oe $end
$var reg 4 E alufs[3:0] $end
$var reg 2 F cs[1:0] $end
$var reg 2 G ns[1:0] $end
$upscope $end
$scope module mem_block_inst $end
$var reg 1 H reset $end
$var reg 1 I clk $end
$var reg 1 J rnw $end
$var reg 12 K addr[11:0] $end
$var reg 16 L data[15:0] $end
$comment memory is not handled $end
$var reg 16 M data_in[15:0] $end
$var reg 16 N data_out[15:0] $end
$upscope $end
$scope module memvalmux_inst $end
$var reg 16 O a[15:0] $end
$var reg 12 P b[11:0] $end
$var reg 1 Q sel $end
$var reg 16 R s[15:0] $end
$upscope $end
$scope module acc_inst $end
$var reg 16 S data_in[15:0] $end
$var reg 1 T acc_ld $end
$var reg 1 U clk $end
$var reg 16 V data_out[15:0] $end
$var reg 1 W accz $end
$var reg 1 X acc15 $end
$var reg 16 Y accumulator[15:0] $end
$upscope $end
$scope module alu_inst $end
$var reg 16 Z a[15:0] $end
$var reg 16 [ b[15:0] $end
$var reg 4 \ alufs[3:0] $end
$var reg 16 ] s[15:0] $end
$upscope $end
$scope module oe_inst $end
$var reg 16 ^ data_in[15:0] $end
$var reg 1 _ clk $end
$var reg 1 ` en $end
$var reg 16 a data_out[15:0] $end
$upscope $end
$scope module ir_inst $end
$var reg 16 b data_in[15:0] $end
$var reg 1 c ir_ld $end
$var reg 1 d clk $end
$var reg 12 e data_out[11:0] $end
$var reg 4 f opcode[3:0] $end
$var reg 16 g data[15:0] $end
$upscope $end
$scope module pc_inst $end
$var reg 16 h data_in[15:0] $end
$var reg 1 i clk $end
$var reg 1 j pc_ld $end
$var reg 1 k pc_inc $end
$var reg 1 l reset $end
$var reg 12 m data_out[11:0] $end
$var reg 12 n counter[11:0] $end
$upscope $end
$scope module pcirmux_inst $end
$var reg 12 o a[11:0] $end
$var reg 12 p b[11:0] $end
$var reg 1 q sel $end
$var reg 12 r s[11:0] $end
$upscope $end
$upscope $end
$upscope $end
$enddefinitions $end
#0
0!
1"
0#
1$
0%
0&
1'
0(
0)
0*
0+
0,
0-
0.
b0000 /
b0000 0
bUUUUUUUUUUUUUUUU 1
bUUUUUUUUUUUUUUUU 2
bUUUUUUUUUUUUUUUU 3
b000000000000 4
b000000000000 5
bUUUUUUUUUUUUUUUU 6
b000000000000 7
08
19
b0000 :
0;
0<
0=
0>
1?
0@
0A
0B
0C
0D
b0000 E
b00 F
b00 G
1H
0I
1J
b000000000000 K
bUUUUUUUUUUUUUUUU L
bUUUUUUUUUUUUUUUU M
bUUUUUUUUUUUUUUUU N
bUUUUUUUUUUUUUUUU O
b000000000000 P
0Q
bUUUUUUUUUUUUUUUU R
bUUUUUUUUUUUUUUUU S
0T
0U
bUUUUUUUUUUUUUUUU V
0W
0X
bUUUUUUUUUUUUUUUU Y
bUUUUUUUUUUUUUUUU Z
bUUUUUUUUUUUUUUUU [
b0000 \
bUUUUUUUUUUUUUUUU ]
bUUUUUUUUUUUUUUUU ^
0_
0`
bUUUUUUUUUUUUUUUU a
bUUUUUUUUUUUUUUUU b
0c
0d
b000000000000 e
b0000 f
b0000000000000000 g
bUUUUUUUUUUUUUUUU h
0i
0j
0k
1l
b000000000000 m
b000000000000 n
b000000000000 o
b000000000000 p
0q
b000000000000 r
#10000000
1!
1#
18
1I
1U
1_
bUUUUUUUUUUUUUUUU a
1d
1i
#20000000
0!
0#
08
0I
0U
0_
0d
0i
#25000000
0"
0$
09
b01 G
0H
0l
#30000000
1!
1#
1*
b0000000100000000 2
b0000000100000000 3
b0000000100000000 6
18
1B
b01 F
b10 G
1I
b0000000100000000 L
b0000000100000000 N
b0000000100000000 O
b0000000100000000 R
b0000000100000000 S
1U
b0000000100000000 [
b0000000100000000 ]
1_
b0000000100000000 a
b0000000100000000 b
1c
1d
b0000000100000000 h
1i
#40000000
0!
0#
08
0I
0U
0_
0d
0i
#50000000
1!
1#
1%
1&
1)
0*
b0000000100000000 2
b0000000100000000 3
b000100000000 4
b000100000000 7
18
1=
1>
1@
0B
b10 F
b11 G
1I
b000100000000 K
b000100000000 P
1Q
b0000000100000000 R
b0000000100000000 S
1U
b0000000100000000 [
b0000000100000000 ]
1_
b0000000100000000 a
0c
1d
b000100000000 e
b0000000100000000 g
b0000000100000000 h
1i
1k
b000100000000 p
1q
b000100000000 r
#60000000
0!
0#
08
0I
0U
0_
0d
0i
#70000000
1!
1#
0%
0&
0)
1+
b0001000100010001 2
b0001000100010001 3
b000000000001 5
b0001000100010001 6
b000000000001 7
18
0=
0>
0@
1C
b11 F
b01 G
1I
b000000000001 K
b0001000100010001 L
b0001000100010001 N
b0001000100010001 O
b000000000001 P
0Q
b0001000100010001 R
b0001000100010001 S
1T
1U
b0001000100010001 [
b0001000100010001 ]
1_
b0001000100010001 a
b0001000100010001 b
1d
b0001000100010001 h
1i
0k
b000000000001 m
b000000000001 n
b000000000001 o
0q
b000000000001 r
#80000000
0!
0#
08
0I
0U
0_
0d
0i
#90000000
1!
1#
1*
0+
1.
b0001000100010001 1
b0010000100000001 2
b0010000100000001 3
b0010000100000001 6
18
1<
1B
0C
b01 F
b10 G
1I
b0010000100000001 L
b0010000100000001 N
b0010000100000001 O
b0010000100000001 R
b0010000100000001 S
0T
1U
b0001000100010001 V
1X
b0001000100010001 Y
b0001000100010001 Z
b0010000100000001 [
b0010000100000001 ]
b0001000100010001 ^
1_
b0010000100000001 a
b0010000100000001 b
1c
1d
b0010000100000001 h
1i
#100000000
0!
0#
08
0I
0U
0_
0d
0i
#110000000
1!
1#
1%
1&
1)
0*
b0010 /
b0010000100000001 2
b0010000100000001 3
b000100000001 4
b000100000001 7
18
b0010 :
1=
1>
1@
0B
b10 F
b11 G
1I
b000100000001 K
b000100000001 P
1Q
b0010000100000001 R
b0010000100000001 S
1U
b0010000100000001 [
b0010000100000001 ]
1_
b0010000100000001 a
0c
1d
b000100000001 e
b0010 f
b0010000100000001 g
b0010000100000001 h
1i
1k
b000100000001 p
1q
b000100000001 r
#120000000
0!
0#
08
0I
0U
0_
0d
0i
#130000000
1!
1#
0%
0&
0)
1+
b0010 0
b0010001000100010 2
b0011001100110011 3
b000000000010 5
b0010001000100010 6
b000000000010 7
18
0=
0>
0@
1C
b0010 E
b11 F
b01 G
1I
b000000000010 K
b0010001000100010 L
b0010001000100010 N
b0010001000100010 O
b000000000010 P
0Q
b0010001000100010 R
b0011001100110011 S
1T
1U
b0010001000100010 [
b0010 \
b0011001100110011 ]
1_
b0010001000100010 a
b0010001000100010 b
1d
b0011001100110011 h
1i
0k
b000000000010 m
b000000000010 n
b000000000010 o
0q
b000000000010 r
#140000000
0!
0#
08
0I
0U
0_
0d
0i
#150000000
1!
1#
1*
0+
b0000 0
b0011001100110011 1
b0110000000000101 2
b0110000000000101 3
b0110000000000101 6
18
1B
0C
b0000 E
b01 F
b10 G
1I
b0110000000000101 L
b0110000000000101 N
b0110000000000101 O
b0110000000000101 R
b0110000000000101 S
0T
1U
b0011001100110011 V
b0011001100110011 Y
b0011001100110011 Z
b0110000000000101 [
b0000 \
b0110000000000101 ]
b0011001100110011 ^
1_
b0110000000000101 a
b0110000000000101 b
1c
1d
b0110000000000101 h
1i
#160000000
0!
0#
08
0I
0U
0_
0d
0i
#170000000
1!
1#
0%
0&
1(
0)
0*
b0110 /
b0110000000000101 2
b0110000000000101 3
b000000000101 4
b000000000010 7
18
b0110 :
0=
0>
0@
1A
0B
b10 F
b11 G
1I
b000000000010 K
b000000000010 P
0Q
b0110000000000101 R
b0110000000000101 S
1U
b0110000000000101 [
b0110000000000101 ]
1_
b0110000000000101 a
0c
1d
b000000000101 e
b0110 f
b0110000000000101 g
b0110000000000101 h
1i
1j
0k
b000000000101 p
0q
b000000000010 r
#180000000
0!
0#
08
0I
0U
0_
0d
0i
#190000000
1!
1#
0(
b000000000101 5
b000000000101 7
18
0A
b11 F
b01 G
1I
b000000000101 K
b000000000101 P
1U
1_
b0110000000000101 a
1d
1i
0j
b000000000101 m
b000000000101 n
b000000000101 o
b000000000101 r
#200000000
0!
0#
08
0I
0U
0_
0d
0i
#210000000
1!
1#
1*
b0010000100000000 2
b0010000100000000 3
b0010000100000000 6
18
1B
b01 F
b10 G
1I
b0010000100000000 L
b0010000100000000 N
b0010000100000000 O
b0010000100000000 R
b0010000100000000 S
1U
b0010000100000000 [
b0010000100000000 ]
1_
b0010000100000000 a
b0010000100000000 b
1c
1d
b0010000100000000 h
1i
#220000000
0!
0#
08
0I
0U
0_
0d
0i
#230000000
1!
1#
1%
1&
0(
1)
0*
b0010 /
b0010000100000000 2
b0010000100000000 3
b000100000000 4
b000100000000 7
18
b0010 :
1=
1>
1@
0A
0B
b10 F
b11 G
1I
b000100000000 K
b000100000000 P
1Q
b0010000100000000 R
b0010000100000000 S
1U
b0010000100000000 [
b0010000100000000 ]
1_
b0010000100000000 a
0c
1d
b000100000000 e
b0010 f
b0010000100000000 g
b0010000100000000 h
1i
0j
1k
b000100000000 p
1q
b000100000000 r
#240000000
0!
0#
08
0I
0U
0_
0d
0i
#250000000
1!
1#
0%
0&
0)
1+
b0010 0
b0001000100010001 2
b0100010001000100 3
b000000000110 5
b0001000100010001 6
b000000000110 7
18
0=
0>
0@
1C
b0010 E
b11 F
b01 G
1I
b000000000110 K
b0001000100010001 L
b0001000100010001 N
b0001000100010001 O
b000000000110 P
0Q
b0001000100010001 R
b0100010001000100 S
1T
1U
b0001000100010001 [
b0010 \
b0100010001000100 ]
1_
b0001000100010001 a
b0001000100010001 b
1d
b0100010001000100 h
1i
0k
b000000000110 m
b000000000110 n
b000000000110 o
0q
b000000000110 r
#260000000
0!
0#
08
0I
0U
0_
0d
0i
#270000000
1!
1#
1*
0+
b0000 0
b0100010001000100 1
b0111000000000000 2
b0111000000000000 3
b0111000000000000 6
18
1B
0C
b0000 E
b01 F
b10 G
1I
b0111000000000000 L
b0111000000000000 N
b0111000000000000 O
b0111000000000000 R
b0111000000000000 S
0T
1U
b0100010001000100 V
b0100010001000100 Y
b0100010001000100 Z
b0111000000000000 [
b0000 \
b0111000000000000 ]
b0100010001000100 ^
1_
b0111000000000000 a
b0111000000000000 b
1c
1d
b0111000000000000 h
1i
#280000000
0!
0#
08
0I
0U
0_
0d
0i
#290000000
1!
1#
0%
0&
0)
0*
b0111 /
b0111000000000000 2
b0111000000000000 3
b000000000000 4
b000000000110 7
18
b0111 :
0=
0>
0@
0B
b10 F
b00 G
1I
b000000000110 K
b000000000110 P
0Q
b0111000000000000 R
b0111000000000000 S
1U
b0111000000000000 [
b0111000000000000 ]
1_
b0111000000000000 a
0c
1d
b000000000000 e
b0111 f
b0111000000000000 g
b0111000000000000 h
1i
0k
b000000000000 p
0q
b000000000110 r
#300000000
0!
0#
08
0I
0U
0_
0d
0i
#310000000
1!
1#
18
b00 F
1I
1U
1_
b0111000000000000 a
1d
1i
#320000000
0!
0#
08
0I
0U
0_
0d
0i
#330000000
1!
1#
18
1I
1U
1_
b0111000000000000 a
1d
1i
#340000000
0!
0#
08
0I
0U
0_
0d
0i
#350000000
1!
1#
18
1I
1U
1_
b0111000000000000 a
1d
1i
#360000000
0!
0#
08
0I
0U
0_
0d
0i
#370000000
1!
1#
18
1I
1U
1_
b0111000000000000 a
1d
1i
#380000000
0!
0#
08
0I
0U
0_
0d
0i
#390000000
1!
1#
18
1I
1U
1_
b0111000000000000 a
1d
1i
#400000000
0!
0#
08
0I
0U
0_
0d
0i
#410000000
1!
1#
18
1I
1U
1_
b0111000000000000 a
1d
1i
#420000000
0!
0#
08
0I
0U
0_
0d
0i
#430000000
1!
1#
18
1I
1U
1_
b0111000000000000 a
1d
1i
#440000000
0!
0#
08
0I
0U
0_
0d
0i
#450000000
1!
1#
18
1I
1U
1_
b0111000000000000 a
1d
1i
#460000000
0!
0#
08
0I
0U
0_
0d
0i
#470000000
1!
1#
18
1I
1U
1_
b0111000000000000 a
1d
1i
#480000000
0!
0#
08
0I
0U
0_
0d
0i
#490000000
1!
1#
18
1I
1U
1_
b0111000000000000 a
1d
1i
#500000000
0!
0#
08
0I
0U
0_
0d
0i
#510000000
1!
1#
18
1I
1U
1_
b0111000000000000 a
1d
1i
#520000000
0!
0#
08
0I
0U
0_
0d
0i
#530000000
1!
1#
18
1I
1U
1_
b0111000000000000 a
1d
1i
#540000000
0!
0#
08
0I
0U
0_
0d
0i
#550000000
1!
1#
18
1I
1U
1_
b0111000000000000 a
1d
1i
#560000000
0!
0#
08
0I
0U
0_
0d
0i
#570000000
1!
1#
18
1I
1U
1_
b0111000000000000 a
1d
1i
#580000000
0!
0#
08
0I
0U
0_
0d
0i
#590000000
1!
1#
18
1I
1U
1_
b0111000000000000 a
1d
1i
#600000000
0!
0#
08
0I
0U
0_
0d
0i
#610000000
1!
1#
18
1I
1U
1_
b0111000000000000 a
1d
1i
#620000000
0!
0#
08
0I
0U
0_
0d
0i
#630000000
1!
1#
18
1I
1U
1_
b0111000000000000 a
1d
1i
#640000000
0!
0#
08
0I
0U
0_
0d
0i
#650000000
1!
1#
18
1I
1U
1_
b0111000000000000 a
1d
1i
#660000000
0!
0#
08
0I
0U
0_
0d
0i
#670000000
1!
1#
18
1I
1U
1_
b0111000000000000 a
1d
1i
#680000000
0!
0#
08
0I
0U
0_
0d
0i
#690000000
1!
1#
18
1I
1U
1_
b0111000000000000 a
1d
1i
#700000000
0!
0#
08
0I
0U
0_
0d
0i
#710000000
1!
1#
18
1I
1U
1_
b0111000000000000 a
1d
1i
#720000000
0!
0#
08
0I
0U
0_
0d
0i
#730000000
1!
1#
18
1I
1U
1_
b0111000000000000 a
1d
1i
#740000000
0!
0#
08
0I
0U
0_
0d
0i
#750000000
1!
1#
18
1I
1U
1_
b0111000000000000 a
1d
1i
#760000000
0!
0#
08
0I
0U
0_
0d
0i
#770000000
1!
1#
18
1I
1U
1_
b0111000000000000 a
1d
1i
#780000000
0!
0#
08
0I
0U
0_
0d
0i
#790000000
1!
1#
18
1I
1U
1_
b0111000000000000 a
1d
1i
#800000000
0!
0#
08
0I
0U
0_
0d
0i
#810000000
1!
1#
18
1I
1U
1_
b0111000000000000 a
1d
1i
#820000000
0!
0#
08
0I
0U
0_
0d
0i
#830000000
1!
1#
18
1I
1U
1_
b0111000000000000 a
1d
1i
#840000000
0!
0#
08
0I
0U
0_
0d
0i
#850000000
1!
1#
18
1I
1U
1_
b0111000000000000 a
1d
1i
#860000000
0!
0#
08
0I
0U
0_
0d
0i
#870000000
1!
1#
18
1I
1U
1_
b0111000000000000 a
1d
1i
#880000000
0!
0#
08
0I
0U
0_
0d
0i
#890000000
1!
1#
18
1I
1U
1_
b0111000000000000 a
1d
1i
#900000000
0!
0#
08
0I
0U
0_
0d
0i
#910000000
1!
1#
18
1I
1U
1_
b0111000000000000 a
1d
1i
#920000000
0!
0#
08
0I
0U
0_
0d
0i
